{"serverId":61,"serverName":"Ereshkigal","date":"01-15-2019","elyos":[{"position":51,"arrowStatus":"STATIC","rankingPositionChange":0,"characterName":"Vivere","characterID":17417,"characterClassID":11,"gloryPoint":1704,"serverName":"Ereshkigal","serverID":61,"soldierRankID":11,"raceID":0,"gloryPointChange":60},{"position":52,"arrowStatus":"STATIC","rankingPositionChange":0,"characterName":"Vankeddol","characterID":2688,"characterClassID":1,"gloryPoint":1508,"guildName":"D a r k  S o l d i e r s","serverName":"Ereshkigal","serverID":61,"guildID":1028,"contributionPoint":523426719,"memberCount":12,"masterName":"Naitsabes","guildLevel":4,"soldierRankID":11,"raceID":0,"gloryPointChange":60},{"position":53,"arrowStatus":"STATIC","rankingPositionChange":0,"characterName":"Kaffee","characterID":16235,"characterClassID":11,"gloryPoint":1444,"serverName":"Ereshkigal","serverID":61,"soldierRankID":11,"raceID":0,"gloryPointChange":0}],"asmodians":[{"position":1,"arrowStatus":"STATIC","rankingPositionChange":0,"characterName":"Tutti","characterID":1286,"characterClassID":7,"gloryPoint":6119,"guildName":" Zero DMG ","serverName":"Ereshkigal","serverID":61,"guildID":1083,"contributionPoint":522971023,"memberCount":9,"masterName":"Tutti","guildLevel":5,"soldierRankID":14,"raceID":1,"gloryPointChange":60},{"position":2,"arrowStatus":"STATIC","rankingPositionChange":0,"characterName":"Yen","characterID":1348,"characterClassID":1,"gloryPoint":6060,"serverName":"Ereshkigal","serverID":61,"soldierRankID":14,"raceID":1,"gloryPointChange":60},{"position":3,"arrowStatus":"STATIC","rankingPositionChange":0,"characterName":"Barkii","characterID":1233,"characterClassID":1,"gloryPoint":6011,"guildName":"White Wolves","serverName":"Ereshkigal","serverID":61,"guildID":1050,"contributionPoint":1475288708,"memberCount":21,"masterName":"Barkii","guildLevel":7,"soldierRankID":14,"raceID":1,"gloryPointChange":60},{"position":4,"arrowStatus":"STATIC","rankingPositionChange":0,"characterName":"Imperia","characterID":1091,"characterClassID":7,"gloryPoint":5891,"guildName":"White Wolves","serverName":"Ereshkigal","serverID":61,"guildID":1050,"contributionPoint":1475288708,"memberCount":21,"masterName":"Barkii","guildLevel":7,"soldierRankID":14,"raceID":1,"gloryPointChange":60},{"position":5,"arrowStatus":"STATIC","rankingPositionChange":0,"characterName":"Frutti","characterID":1290,"characterClassID":10,"gloryPoint":5854,"guildName":" Zero DMG ","serverName":"Ereshkigal","serverID":61,"guildID":1083,"contributionPoint":522971023,"memberCount":9,"masterName":"Tutti","guildLevel":5,"soldierRankID":14,"raceID":1,"gloryPointChange":60},{"position":6,"arrowStatus":"STATIC","rankingPositionChange":0,"characterName":"Srsly","characterID":2269,"characterClassID":1,"gloryPoint":5651,"guildName":" Zero DMG ","serverName":"Ereshkigal","serverID":61,"guildID":1083,"contributionPoint":522971023,"memberCount":9,"masterName":"Tutti","guildLevel":5,"soldierRankID":14,"raceID":1,"gloryPointChange":60},{"position":7,"arrowStatus":"STATIC","rankingPositionChange":0,"characterName":"Neela","characterID":1323,"characterClassID":11,"gloryPoint":5454,"guildName":"White Wolves","serverName":"Ereshkigal","serverID":61,"guildID":1050,"contributionPoint":1475288708,"memberCount":21,"masterName":"Barkii","guildLevel":7,"soldierRankID":14,"raceID":1,"gloryPointChange":60},{"position":8,"arrowStatus":"STATIC","rankingPositionChange":0,"characterName":"Quinn","characterID":1308,"characterClassID":11,"gloryPoint":5210,"guildName":"NO PAIN NO GAIN","serverName":"Ereshkigal","serverID":61,"guildID":1051,"contributionPoint":132572885,"memberCount":17,"masterName":"Eko","guildLevel":4,"soldierRankID":14,"raceID":1,"gloryPointChange":60},{"position":9,"arrowStatus":"STATIC","rankingPositionChange":0,"characterName":"Aiwa","characterID":1668,"characterClassID":4,"gloryPoint":5182,"serverName":"Ereshkigal","serverID":61,"soldierRankID":13,"raceID":1,"gloryPointChange":60},{"position":10,"arrowStatus":"STATIC","rankingPositionChange":0,"characterName":"Deathchieff","characterID":4558,"characterClassID":11,"gloryPoint":5078,"guildName":"White Wolves","serverName":"Ereshkigal","serverID":61,"guildID":1050,"contributionPoint":1475288708,"memberCount":21,"masterName":"Barkii","guildLevel":7,"soldierRankID":13,"raceID":1,"gloryPointChange":60},{"position":11,"arrowStatus":"STATIC","rankingPositionChange":0,"characterName":"Kazihl","characterID":1082,"characterClassID":11,"gloryPoint":4892,"guildName":" Zero DMG ","serverName":"Ereshkigal","serverID":61,"guildID":1083,"contributionPoint":522971023,"memberCount":9,"masterName":"Tutti","guildLevel":5,"soldierRankID":13,"raceID":1,"gloryPointChange":60},{"position":12,"arrowStatus":"STATIC","rankingPositionChange":0,"characterName":"Kampfhenne","characterID":4304,"characterClassID":11,"gloryPoint":4628,"guildName":"White Wolves","serverName":"Ereshkigal","serverID":61,"guildID":1050,"contributionPoint":1475288708,"memberCount":21,"masterName":"Barkii","guildLevel":7,"soldierRankID":13,"raceID":1,"gloryPointChange":60},{"position":13,"arrowStatus":"STATIC","rankingPositionChange":0,"characterName":"Calinca","characterID":4893,"characterClassID":11,"gloryPoint":4550,"serverName":"Ereshkigal","serverID":61,"soldierRankID":13,"raceID":1,"gloryPointChange":60},{"position":14,"arrowStatus":"STATIC","rankingPositionChange":0,"characterName":"Xxviktorxx","characterID":13824,"characterClassID":13,"gloryPoint":4444,"guildName":" Zero DMG ","serverName":"Ereshkigal","serverID":61,"guildID":1083,"contributionPoint":522971023,"memberCount":9,"masterName":"Tutti","guildLevel":5,"soldierRankID":13,"raceID":1,"gloryPointChange":60},{"position":15,"arrowStatus":"STATIC","rankingPositionChange":0,"characterName":"Mantranuss","characterID":2352,"characterClassID":11,"gloryPoint":4250,"serverName":"Ereshkigal","serverID":61,"soldierRankID":13,"raceID":1,"gloryPointChange":0},{"position":16,"arrowStatus":"STATIC","rankingPositionChange":0,"characterName":"Sarho","characterID":5936,"characterClassID":5,"gloryPoint":3911,"guildName":"White Wolves","serverName":"Ereshkigal","serverID":61,"guildID":1050,"contributionPoint":1475288708,"memberCount":21,"masterName":"Barkii","guildLevel":7,"soldierRankID":13,"raceID":1,"gloryPointChange":0},{"position":17,"arrowStatus":"STATIC","rankingPositionChange":0,"characterName":"Pando","characterID":1936,"characterClassID":16,"gloryPoint":3898,"guildName":" Zero DMG ","serverName":"Ereshkigal","serverID":61,"guildID":1083,"contributionPoint":522971023,"memberCount":9,"masterName":"Tutti","guildLevel":5,"soldierRankID":13,"raceID":1,"gloryPointChange":60},{"position":18,"arrowStatus":"STATIC","rankingPositionChange":0,"characterName":"Eko","characterID":2113,"characterClassID":4,"gloryPoint":3889,"guildName":"NO PAIN NO GAIN","serverName":"Ereshkigal","serverID":61,"guildID":1051,"contributionPoint":132572885,"memberCount":17,"masterName":"Eko","guildLevel":4,"soldierRankID":13,"raceID":1,"gloryPointChange":60},{"position":19,"arrowStatus":"UP","rankingPositionChange":1,"characterName":"Calipso","characterID":8890,"characterClassID":16,"gloryPoint":3782,"serverName":"Ereshkigal","serverID":61,"soldierRankID":13,"raceID":1,"gloryPointChange":60},{"position":20,"arrowStatus":"DOWN","rankingPositionChange":-1,"characterName":"Kayk","characterID":1750,"characterClassID":5,"gloryPoint":3774,"guildName":"White Wolves","serverName":"Ereshkigal","serverID":61,"guildID":1050,"contributionPoint":1475288708,"memberCount":21,"masterName":"Barkii","guildLevel":7,"soldierRankID":13,"raceID":1,"gloryPointChange":0},{"position":21,"arrowStatus":"STATIC","rankingPositionChange":0,"characterName":"Schnulli","characterID":2690,"characterClassID":10,"gloryPoint":3770,"serverName":"Ereshkigal","serverID":61,"soldierRankID":13,"raceID":1,"gloryPointChange":60},{"position":22,"arrowStatus":"STATIC","rankingPositionChange":0,"characterName":"Jaylin","characterID":1159,"characterClassID":16,"gloryPoint":3752,"serverName":"Ereshkigal","serverID":61,"soldierRankID":13,"raceID":1,"gloryPointChange":60},{"position":23,"arrowStatus":"STATIC","rankingPositionChange":0,"characterName":"Afghansuperman","characterID":1438,"characterClassID":1,"gloryPoint":3168,"guildName":" Zero DMG ","serverName":"Ereshkigal","serverID":61,"guildID":1083,"contributionPoint":522971023,"memberCount":9,"masterName":"Tutti","guildLevel":5,"soldierRankID":13,"raceID":1,"gloryPointChange":0},{"position":24,"arrowStatus":"STATIC","rankingPositionChange":0,"characterName":"Beo","characterID":20676,"characterClassID":1,"gloryPoint":3064,"serverName":"Ereshkigal","serverID":61,"soldierRankID":13,"raceID":1,"gloryPointChange":0},{"position":25,"arrowStatus":"STATIC","rankingPositionChange":0,"characterName":"Firebanger","characterID":8098,"characterClassID":5,"gloryPoint":2923,"guildName":"White Wolves","serverName":"Ereshkigal","serverID":61,"guildID":1050,"contributionPoint":1475288708,"memberCount":21,"masterName":"Barkii","guildLevel":7,"soldierRankID":12,"raceID":1,"gloryPointChange":0},{"position":26,"arrowStatus":"STATIC","rankingPositionChange":0,"characterName":"Eksitus","characterID":21644,"characterClassID":8,"gloryPoint":2658,"serverName":"Ereshkigal","serverID":61,"soldierRankID":12,"raceID":1,"gloryPointChange":60},{"position":27,"arrowStatus":"STATIC","rankingPositionChange":0,"characterName":"Momori","characterID":20947,"characterClassID":1,"gloryPoint":2648,"serverName":"Ereshkigal","serverID":61,"soldierRankID":12,"raceID":1,"gloryPointChange":60},{"position":28,"arrowStatus":"STATIC","rankingPositionChange":0,"characterName":"Kentoky","characterID":1415,"characterClassID":8,"gloryPoint":2556,"serverName":"Ereshkigal","serverID":61,"soldierRankID":12,"raceID":1,"gloryPointChange":0},{"position":29,"arrowStatus":"STATIC","rankingPositionChange":0,"characterName":"Valla","characterID":14538,"characterClassID":10,"gloryPoint":2528,"serverName":"Ereshkigal","serverID":61,"soldierRankID":12,"raceID":1,"gloryPointChange":0},{"position":30,"arrowStatus":"STATIC","rankingPositionChange":0,"characterName":"Isa","characterID":4559,"characterClassID":4,"gloryPoint":2498,"guildName":"NO PAIN NO GAIN","serverName":"Ereshkigal","serverID":61,"guildID":1051,"contributionPoint":132572885,"memberCount":17,"masterName":"Eko","guildLevel":4,"soldierRankID":12,"raceID":1,"gloryPointChange":0},{"position":31,"arrowStatus":"STATIC","rankingPositionChange":0,"characterName":"Febreze","characterID":1669,"characterClassID":7,"gloryPoint":2410,"serverName":"Ereshkigal","serverID":61,"soldierRankID":12,"raceID":1,"gloryPointChange":0},{"position":32,"arrowStatus":"STATIC","rankingPositionChange":0,"characterName":"Izzih","characterID":9543,"characterClassID":16,"gloryPoint":2395,"serverName":"Ereshkigal","serverID":61,"soldierRankID":12,"raceID":1,"gloryPointChange":0},{"position":33,"arrowStatus":"STATIC","rankingPositionChange":0,"characterName":"Aurelie","characterID":20217,"characterClassID":10,"gloryPoint":2390,"serverName":"Ereshkigal","serverID":61,"soldierRankID":12,"raceID":1,"gloryPointChange":0},{"position":34,"arrowStatus":"UP","rankingPositionChange":1,"characterName":"Blackknight","characterID":2757,"characterClassID":2,"gloryPoint":2370,"serverName":"Ereshkigal","serverID":61,"soldierRankID":12,"raceID":1,"gloryPointChange":60},{"position":35,"arrowStatus":"UP","rankingPositionChange":1,"characterName":"Forever","characterID":12973,"characterClassID":1,"gloryPoint":2362,"serverName":"Ereshkigal","serverID":61,"soldierRankID":12,"raceID":1,"gloryPointChange":60},{"position":36,"arrowStatus":"UP","rankingPositionChange":1,"characterName":"Stellarossa","characterID":13022,"characterClassID":16,"gloryPoint":2360,"guildName":" Zero DMG ","serverName":"Ereshkigal","serverID":61,"guildID":1083,"contributionPoint":522971023,"memberCount":9,"masterName":"Tutti","guildLevel":5,"soldierRankID":12,"raceID":1,"gloryPointChange":60},{"position":37,"arrowStatus":"DOWN","rankingPositionChange":-3,"characterName":"Soreii","characterID":5274,"characterClassID":7,"gloryPoint":2356,"serverName":"Ereshkigal","serverID":61,"soldierRankID":12,"raceID":1,"gloryPointChange":0},{"position":38,"arrowStatus":"STATIC","rankingPositionChange":0,"characterName":"Chaiva","characterID":20671,"characterClassID":10,"gloryPoint":2270,"serverName":"Ereshkigal","serverID":61,"soldierRankID":12,"raceID":1,"gloryPointChange":0},{"position":39,"arrowStatus":"STATIC","rankingPositionChange":0,"characterName":"Mazikeen","characterID":5449,"characterClassID":11,"gloryPoint":2188,"serverName":"Ereshkigal","serverID":61,"soldierRankID":12,"raceID":1,"gloryPointChange":0},{"position":40,"arrowStatus":"STATIC","rankingPositionChange":0,"characterName":"Shini","characterID":7786,"characterClassID":13,"gloryPoint":2158,"serverName":"Ereshkigal","serverID":61,"soldierRankID":12,"raceID":1,"gloryPointChange":0},{"position":41,"arrowStatus":"STATIC","rankingPositionChange":null,"characterName":"Jellyberry","characterID":6541,"characterClassID":11,"gloryPoint":2142,"serverName":"Ereshkigal","serverID":61,"soldierRankID":12,"raceID":1,"gloryPointChange":null},{"position":42,"arrowStatus":"DOWN","rankingPositionChange":-1,"characterName":"Tami","characterID":11874,"characterClassID":11,"gloryPoint":2114,"serverName":"Ereshkigal","serverID":61,"soldierRankID":12,"raceID":1,"gloryPointChange":0},{"position":43,"arrowStatus":"DOWN","rankingPositionChange":-1,"characterName":"Ulgrim","characterID":19905,"characterClassID":2,"gloryPoint":2088,"serverName":"Ereshkigal","serverID":61,"soldierRankID":12,"raceID":1,"gloryPointChange":0},{"position":44,"arrowStatus":"DOWN","rankingPositionChange":-1,"characterName":"Ysera","characterID":1679,"characterClassID":8,"gloryPoint":2046,"guildName":"White Wolves","serverName":"Ereshkigal","serverID":61,"guildID":1050,"contributionPoint":1475288708,"memberCount":21,"masterName":"Barkii","guildLevel":7,"soldierRankID":12,"raceID":1,"gloryPointChange":0},{"position":45,"arrowStatus":"DOWN","rankingPositionChange":-1,"characterName":"Dotti","characterID":23507,"characterClassID":8,"gloryPoint":1824,"guildName":" Zero DMG ","serverName":"Ereshkigal","serverID":61,"guildID":1083,"contributionPoint":522971023,"memberCount":9,"masterName":"Tutti","guildLevel":5,"soldierRankID":11,"raceID":1,"gloryPointChange":60},{"position":46,"arrowStatus":"STATIC","rankingPositionChange":0,"characterName":"Bebob","characterID":21016,"characterClassID":2,"gloryPoint":1710,"guildName":"White Wolves","serverName":"Ereshkigal","serverID":61,"guildID":1050,"contributionPoint":1475288708,"memberCount":21,"masterName":"Barkii","guildLevel":7,"soldierRankID":11,"raceID":1,"gloryPointChange":60},{"position":47,"arrowStatus":"DOWN","rankingPositionChange":-2,"characterName":"Lowenna","characterID":20539,"characterClassID":8,"gloryPoint":1700,"serverName":"Ereshkigal","serverID":61,"soldierRankID":11,"raceID":1,"gloryPointChange":0},{"position":48,"arrowStatus":"DOWN","rankingPositionChange":-1,"characterName":"Ezaria","characterID":1216,"characterClassID":16,"gloryPoint":1548,"serverName":"Ereshkigal","serverID":61,"soldierRankID":11,"raceID":1,"gloryPointChange":0},{"position":49,"arrowStatus":"DOWN","rankingPositionChange":-1,"characterName":"Haimdal","characterID":17859,"characterClassID":2,"gloryPoint":1518,"guildName":"White Wolves","serverName":"Ereshkigal","serverID":61,"guildID":1050,"contributionPoint":1475288708,"memberCount":21,"masterName":"Barkii","guildLevel":7,"soldierRankID":11,"raceID":1,"gloryPointChange":60},{"position":50,"arrowStatus":"DOWN","rankingPositionChange":null,"characterName":"Blowi","characterID":17581,"characterClassID":5,"gloryPoint":1290,"guildName":"White Wolves","serverName":"Ereshkigal","serverID":61,"guildID":1050,"contributionPoint":1475288708,"memberCount":21,"masterName":"Barkii","guildLevel":7,"soldierRankID":10,"raceID":1,"gloryPointChange":null}],"errors":[0],"dates":{"previous":"01-14-2019"},"stats":{"elyos":{"topHP":{"characterName":"Vivere","characterID":17417,"gloryPointChange":60},"topPositionChange":null,"lowerPositionChange":null},"asmodians":{"topHP":{"characterName":"Tutti","characterID":1286,"guildName":" Zero DMG ","guildID":1083,"gloryPointChange":60},"topPositionChange":{"characterName":"Calipso","characterID":8890,"rankingPositionChange":1},"lowerPositionChange":{"characterName":"Soreii","characterID":5274,"rankingPositionChange":-3}}}}