{"elyos":[{"position":1,"arrowStatus":"UP","rankingPositionChange":1,"characterName":"Madara","characterID":1259,"characterClassID":16,"gloryPoint":284405,"guildName":"White Shadow","serverName":"Miren","serverID":59,"guildID":1281,"contributionPoint":62751908,"memberCount":5,"masterName":"Sasuke","guildLevel":3,"soldierRankID":18,"raceID":0,"gloryPointChange":5928},{"position":2,"arrowStatus":"DOWN","rankingPositionChange":-1,"characterName":"Maniek","characterID":1015,"characterClassID":10,"gloryPoint":284323,"guildName":"Fearless","serverName":"Miren","serverID":59,"guildID":1036,"contributionPoint":231268699,"memberCount":87,"masterName":"Maniek","guildLevel":5,"soldierRankID":17,"raceID":0,"gloryPointChange":2693},{"position":3,"arrowStatus":"STATIC","rankingPositionChange":0,"characterName":"Sasuke","characterID":1219,"characterClassID":16,"gloryPoint":267504,"guildName":"White Shadow","serverName":"Miren","serverID":59,"guildID":1281,"contributionPoint":62751908,"memberCount":5,"masterName":"Sasuke","guildLevel":3,"soldierRankID":17,"raceID":0,"gloryPointChange":4794},{"position":4,"arrowStatus":"STATIC","rankingPositionChange":0,"characterName":"Freelive","characterID":4996,"characterClassID":8,"gloryPoint":210597,"guildName":"Fluffy Haters","serverName":"Miren","serverID":59,"guildID":1188,"contributionPoint":292993537,"memberCount":32,"masterName":"Reinholt","guildLevel":5,"soldierRankID":16,"raceID":0,"gloryPointChange":4431},{"position":5,"arrowStatus":"STATIC","rankingPositionChange":0,"characterName":"Rzadziaczek","characterID":5138,"characterClassID":10,"gloryPoint":198757,"serverName":"Miren","serverID":59,"soldierRankID":16,"raceID":0,"gloryPointChange":540},{"position":6,"arrowStatus":"STATIC","rankingPositionChange":0,"characterName":"Sylwia","characterID":1345,"characterClassID":8,"gloryPoint":183029,"guildName":"Nivis","serverName":"Miren","serverID":59,"guildID":1442,"contributionPoint":58436160,"memberCount":15,"masterName":"Leonik","guildLevel":5,"soldierRankID":16,"raceID":0,"gloryPointChange":100},{"position":7,"arrowStatus":"STATIC","rankingPositionChange":0,"characterName":"Lizabeeth","characterID":1825,"characterClassID":10,"gloryPoint":162386,"guildName":"Fearless","serverName":"Miren","serverID":59,"guildID":1036,"contributionPoint":231268699,"memberCount":87,"masterName":"Maniek","guildLevel":5,"soldierRankID":16,"raceID":0,"gloryPointChange":0},{"position":8,"arrowStatus":"STATIC","rankingPositionChange":0,"characterName":"Beyonder","characterID":2812,"characterClassID":7,"gloryPoint":154884,"guildName":"Fluffy Haters","serverName":"Miren","serverID":59,"guildID":1188,"contributionPoint":292993537,"memberCount":32,"masterName":"Reinholt","guildLevel":5,"soldierRankID":16,"raceID":0,"gloryPointChange":0},{"position":9,"arrowStatus":"STATIC","rankingPositionChange":0,"characterName":"Thorrand","characterID":10008,"characterClassID":8,"gloryPoint":140022,"serverName":"Miren","serverID":59,"soldierRankID":16,"raceID":0,"gloryPointChange":681},{"position":10,"arrowStatus":"STATIC","rankingPositionChange":0,"characterName":"Dainese","characterID":8348,"characterClassID":4,"gloryPoint":137752,"guildName":"Nivis","serverName":"Miren","serverID":59,"guildID":1442,"contributionPoint":58436160,"memberCount":15,"masterName":"Leonik","guildLevel":5,"soldierRankID":16,"raceID":0,"gloryPointChange":0},{"position":11,"arrowStatus":"STATIC","rankingPositionChange":0,"characterName":"Sorey","characterID":22096,"characterClassID":10,"gloryPoint":127493,"guildName":"Secretive","serverName":"Miren","serverID":59,"guildID":1072,"contributionPoint":134319260,"memberCount":9,"masterName":"Sali","guildLevel":6,"soldierRankID":15,"raceID":0,"gloryPointChange":0},{"position":12,"arrowStatus":"STATIC","rankingPositionChange":0,"characterName":"Gwiazdeczka","characterID":4490,"characterClassID":14,"gloryPoint":117150,"guildName":"Fearless","serverName":"Miren","serverID":59,"guildID":1036,"contributionPoint":231268699,"memberCount":87,"masterName":"Maniek","guildLevel":5,"soldierRankID":15,"raceID":0,"gloryPointChange":49},{"position":13,"arrowStatus":"STATIC","rankingPositionChange":0,"characterName":"Kailena","characterID":27312,"characterClassID":16,"gloryPoint":102598,"serverName":"Miren","serverID":59,"soldierRankID":15,"raceID":0,"gloryPointChange":1570},{"position":14,"arrowStatus":"STATIC","rankingPositionChange":0,"characterName":"Neoka","characterID":30380,"characterClassID":14,"gloryPoint":102416,"serverName":"Miren","serverID":59,"soldierRankID":15,"raceID":0,"gloryPointChange":1520},{"position":15,"arrowStatus":"STATIC","rankingPositionChange":0,"characterName":"Oficer","characterID":1381,"characterClassID":8,"gloryPoint":98748,"guildName":"Nivis","serverName":"Miren","serverID":59,"guildID":1442,"contributionPoint":58436160,"memberCount":15,"masterName":"Leonik","guildLevel":5,"soldierRankID":15,"raceID":0,"gloryPointChange":0},{"position":16,"arrowStatus":"UP","rankingPositionChange":1,"characterName":"Sacha","characterID":2470,"characterClassID":10,"gloryPoint":98522,"serverName":"Miren","serverID":59,"soldierRankID":15,"raceID":0,"gloryPointChange":1211},{"position":17,"arrowStatus":"DOWN","rankingPositionChange":-1,"characterName":"Sayent","characterID":1048,"characterClassID":10,"gloryPoint":98226,"guildName":"Secretive","serverName":"Miren","serverID":59,"guildID":1072,"contributionPoint":134319260,"memberCount":9,"masterName":"Sali","guildLevel":6,"soldierRankID":15,"raceID":0,"gloryPointChange":0},{"position":18,"arrowStatus":"STATIC","rankingPositionChange":0,"characterName":"Chyszwar","characterID":4266,"characterClassID":10,"gloryPoint":92012,"serverName":"Miren","serverID":59,"soldierRankID":15,"raceID":0,"gloryPointChange":50},{"position":19,"arrowStatus":"STATIC","rankingPositionChange":0,"characterName":"Szmacina","characterID":26471,"characterClassID":1,"gloryPoint":90347,"guildName":"  C H U L I G A N K A  ","serverName":"Miren","serverID":59,"guildID":1057,"contributionPoint":205754304,"memberCount":60,"masterName":"Ribon","guildLevel":6,"soldierRankID":15,"raceID":0,"gloryPointChange":779},{"position":20,"arrowStatus":"STATIC","rankingPositionChange":0,"characterName":"Mel","characterID":5543,"characterClassID":10,"gloryPoint":82848,"guildName":"Fluffy Haters","serverName":"Miren","serverID":59,"guildID":1188,"contributionPoint":292993537,"memberCount":32,"masterName":"Reinholt","guildLevel":5,"soldierRankID":15,"raceID":0,"gloryPointChange":0},{"position":21,"arrowStatus":"STATIC","rankingPositionChange":0,"characterName":"Rafall","characterID":19916,"characterClassID":14,"gloryPoint":81968,"guildName":"  C H U L I G A N K A  ","serverName":"Miren","serverID":59,"guildID":1057,"contributionPoint":205754304,"memberCount":60,"masterName":"Ribon","guildLevel":6,"soldierRankID":15,"raceID":0,"gloryPointChange":1593},{"position":22,"arrowStatus":"STATIC","rankingPositionChange":0,"characterName":"Trafialny","characterID":27637,"characterClassID":13,"gloryPoint":70382,"guildName":"  C H U L I G A N K A  ","serverName":"Miren","serverID":59,"guildID":1057,"contributionPoint":205754304,"memberCount":60,"masterName":"Ribon","guildLevel":6,"soldierRankID":15,"raceID":0,"gloryPointChange":329},{"position":23,"arrowStatus":"STATIC","rankingPositionChange":0,"characterName":"Light","characterID":10654,"characterClassID":16,"gloryPoint":69174,"guildName":"  C H U L I G A N K A  ","serverName":"Miren","serverID":59,"guildID":1057,"contributionPoint":205754304,"memberCount":60,"masterName":"Ribon","guildLevel":6,"soldierRankID":15,"raceID":0,"gloryPointChange":450},{"position":24,"arrowStatus":"STATIC","rankingPositionChange":1,"characterName":"Deathsky","characterID":15578,"characterClassID":2,"gloryPoint":67603,"guildName":"Sparta","serverName":"Miren","serverID":59,"guildID":1144,"contributionPoint":39323309,"memberCount":27,"masterName":"Anginsan","guildLevel":5,"soldierRankID":15,"raceID":0,"gloryPointChange":610},{"position":25,"arrowStatus":"STATIC","rankingPositionChange":-1,"characterName":"Reinholt","characterID":1911,"characterClassID":11,"gloryPoint":67449,"guildName":"Fluffy Haters","serverName":"Miren","serverID":59,"guildID":1188,"contributionPoint":292993537,"memberCount":32,"masterName":"Reinholt","guildLevel":5,"soldierRankID":15,"raceID":0,"gloryPointChange":0},{"position":26,"arrowStatus":"STATIC","rankingPositionChange":0,"characterName":"Ribon","characterID":5136,"characterClassID":1,"gloryPoint":61408,"guildName":"  C H U L I G A N K A  ","serverName":"Miren","serverID":59,"guildID":1057,"contributionPoint":205754304,"memberCount":60,"masterName":"Ribon","guildLevel":6,"soldierRankID":15,"raceID":0,"gloryPointChange":1255},{"position":27,"arrowStatus":"STATIC","rankingPositionChange":0,"characterName":"Vivian","characterID":1649,"characterClassID":16,"gloryPoint":59641,"serverName":"Miren","serverID":59,"soldierRankID":15,"raceID":0,"gloryPointChange":0},{"position":28,"arrowStatus":"STATIC","rankingPositionChange":1,"characterName":"Anjali","characterID":28026,"characterClassID":10,"gloryPoint":58965,"serverName":"Miren","serverID":59,"soldierRankID":15,"raceID":0,"gloryPointChange":1655},{"position":29,"arrowStatus":"STATIC","rankingPositionChange":-1,"characterName":"Erroor","characterID":5564,"characterClassID":2,"gloryPoint":58103,"guildName":"  C H U L I G A N K A  ","serverName":"Miren","serverID":59,"guildID":1057,"contributionPoint":205754304,"memberCount":60,"masterName":"Ribon","guildLevel":6,"soldierRankID":15,"raceID":0,"gloryPointChange":657},{"position":30,"arrowStatus":"STATIC","rankingPositionChange":1,"characterName":"Anginsan","characterID":14913,"characterClassID":14,"gloryPoint":52077,"guildName":"Sparta","serverName":"Miren","serverID":59,"guildID":1144,"contributionPoint":39323309,"memberCount":27,"masterName":"Anginsan","guildLevel":5,"soldierRankID":15,"raceID":0,"gloryPointChange":360},{"position":31,"arrowStatus":"STATIC","rankingPositionChange":-1,"characterName":"Caelia","characterID":14341,"characterClassID":14,"gloryPoint":51796,"guildName":"IX Legion","serverName":"Miren","serverID":59,"guildID":1372,"contributionPoint":24575361,"memberCount":22,"masterName":"Orzechpn","guildLevel":6,"soldierRankID":14,"raceID":0,"gloryPointChange":0},{"position":32,"arrowStatus":"STATIC","rankingPositionChange":0,"characterName":"Yamushido","characterID":16012,"characterClassID":2,"gloryPoint":50924,"guildName":"Fluffy Haters","serverName":"Miren","serverID":59,"guildID":1188,"contributionPoint":292993537,"memberCount":32,"masterName":"Reinholt","guildLevel":5,"soldierRankID":14,"raceID":0,"gloryPointChange":0},{"position":33,"arrowStatus":"STATIC","rankingPositionChange":0,"characterName":"Franz","characterID":13932,"characterClassID":2,"gloryPoint":50691,"guildName":"Sparta","serverName":"Miren","serverID":59,"guildID":1144,"contributionPoint":39323309,"memberCount":27,"masterName":"Anginsan","guildLevel":5,"soldierRankID":14,"raceID":0,"gloryPointChange":360},{"position":34,"arrowStatus":"STATIC","rankingPositionChange":0,"characterName":"Sikra","characterID":27309,"characterClassID":1,"gloryPoint":48941,"serverName":"Miren","serverID":59,"soldierRankID":14,"raceID":0,"gloryPointChange":540},{"position":35,"arrowStatus":"STATIC","rankingPositionChange":0,"characterName":"Pierozek","characterID":9949,"characterClassID":8,"gloryPoint":47387,"guildName":"InVictus","serverName":"Miren","serverID":59,"guildID":1251,"contributionPoint":49997091,"memberCount":19,"masterName":"Mazen","guildLevel":6,"soldierRankID":14,"raceID":0,"gloryPointChange":0},{"position":36,"arrowStatus":"STATIC","rankingPositionChange":0,"characterName":"Darcia","characterID":30757,"characterClassID":4,"gloryPoint":45656,"guildName":"  C H U L I G A N K A  ","serverName":"Miren","serverID":59,"guildID":1057,"contributionPoint":205754304,"memberCount":60,"masterName":"Ribon","guildLevel":6,"soldierRankID":14,"raceID":0,"gloryPointChange":0},{"position":37,"arrowStatus":"UP","rankingPositionChange":1,"characterName":"Pepitka","characterID":28074,"characterClassID":2,"gloryPoint":43176,"serverName":"Miren","serverID":59,"soldierRankID":14,"raceID":0,"gloryPointChange":1020},{"position":38,"arrowStatus":"DOWN","rankingPositionChange":-1,"characterName":"Leonik","characterID":18448,"characterClassID":11,"gloryPoint":42636,"guildName":"Nivis","serverName":"Miren","serverID":59,"guildID":1442,"contributionPoint":58436160,"memberCount":15,"masterName":"Leonik","guildLevel":5,"soldierRankID":14,"raceID":0,"gloryPointChange":0},{"position":39,"arrowStatus":"STATIC","rankingPositionChange":0,"characterName":"Ajane","characterID":28103,"characterClassID":13,"gloryPoint":41674,"serverName":"Miren","serverID":59,"soldierRankID":14,"raceID":0,"gloryPointChange":630},{"position":40,"arrowStatus":"STATIC","rankingPositionChange":0,"characterName":"Ostra","characterID":8735,"characterClassID":10,"gloryPoint":39605,"guildName":"Nivis","serverName":"Miren","serverID":59,"guildID":1442,"contributionPoint":58436160,"memberCount":15,"masterName":"Leonik","guildLevel":5,"soldierRankID":14,"raceID":0,"gloryPointChange":0},{"position":41,"arrowStatus":"STATIC","rankingPositionChange":0,"characterName":"Kaillena","characterID":30386,"characterClassID":4,"gloryPoint":37893,"serverName":"Miren","serverID":59,"soldierRankID":14,"raceID":0,"gloryPointChange":420},{"position":42,"arrowStatus":"STATIC","rankingPositionChange":0,"characterName":"Neit","characterID":26859,"characterClassID":4,"gloryPoint":34606,"guildName":"SuicideSquad","serverName":"Miren","serverID":59,"guildID":1533,"contributionPoint":3687122,"memberCount":3,"masterName":"Neit","guildLevel":1,"soldierRankID":14,"raceID":0,"gloryPointChange":0},{"position":43,"arrowStatus":"STATIC","rankingPositionChange":0,"characterName":"Nefrete","characterID":29808,"characterClassID":10,"gloryPoint":34024,"guildName":"InVictus","serverName":"Miren","serverID":59,"guildID":1251,"contributionPoint":49997091,"memberCount":19,"masterName":"Mazen","guildLevel":6,"soldierRankID":14,"raceID":0,"gloryPointChange":12},{"position":44,"arrowStatus":"STATIC","rankingPositionChange":0,"characterName":"Masakrzyciel","characterID":29242,"characterClassID":10,"gloryPoint":32384,"guildName":"  C H U L I G A N K A  ","serverName":"Miren","serverID":59,"guildID":1057,"contributionPoint":205754304,"memberCount":60,"masterName":"Ribon","guildLevel":6,"soldierRankID":14,"raceID":0,"gloryPointChange":25},{"position":45,"arrowStatus":"STATIC","rankingPositionChange":0,"characterName":"Ejko","characterID":30381,"characterClassID":16,"gloryPoint":31679,"serverName":"Miren","serverID":59,"soldierRankID":14,"raceID":0,"gloryPointChange":60},{"position":46,"arrowStatus":"STATIC","rankingPositionChange":1,"characterName":"Naromi","characterID":30382,"characterClassID":7,"gloryPoint":30809,"serverName":"Miren","serverID":59,"soldierRankID":14,"raceID":0,"gloryPointChange":540},{"position":47,"arrowStatus":"STATIC","rankingPositionChange":-1,"characterName":"Jefrej","characterID":27544,"characterClassID":5,"gloryPoint":30448,"serverName":"Miren","serverID":59,"soldierRankID":14,"raceID":0,"gloryPointChange":0},{"position":48,"arrowStatus":"STATIC","rankingPositionChange":0,"characterName":"Ufkooo","characterID":5429,"characterClassID":10,"gloryPoint":30218,"guildName":"Fluffy Haters","serverName":"Miren","serverID":59,"guildID":1188,"contributionPoint":292993537,"memberCount":32,"masterName":"Reinholt","guildLevel":5,"soldierRankID":14,"raceID":0,"gloryPointChange":0},{"position":49,"arrowStatus":"STATIC","rankingPositionChange":0,"characterName":"Hisakari","characterID":1765,"characterClassID":5,"gloryPoint":29956,"guildName":"  C H U L I G A N K A  ","serverName":"Miren","serverID":59,"guildID":1057,"contributionPoint":205754304,"memberCount":60,"masterName":"Ribon","guildLevel":6,"soldierRankID":14,"raceID":0,"gloryPointChange":178},{"position":50,"arrowStatus":"STATIC","rankingPositionChange":0,"characterName":"Maila","characterID":3364,"characterClassID":16,"gloryPoint":29392,"guildName":"  C H U L I G A N K A  ","serverName":"Miren","serverID":59,"guildID":1057,"contributionPoint":205754304,"memberCount":60,"masterName":"Ribon","guildLevel":6,"soldierRankID":14,"raceID":0,"gloryPointChange":490},{"position":51,"arrowStatus":"STATIC","rankingPositionChange":1,"characterName":"Kudzia","characterID":38407,"characterClassID":14,"gloryPoint":25853,"guildName":"Fearless","serverName":"Miren","serverID":59,"guildID":1036,"contributionPoint":231268699,"memberCount":87,"masterName":"Maniek","guildLevel":5,"soldierRankID":14,"raceID":0,"gloryPointChange":470},{"position":52,"arrowStatus":"STATIC","rankingPositionChange":-1,"characterName":"Barylka","characterID":23268,"characterClassID":7,"gloryPoint":25497,"guildName":"Fluffy Haters","serverName":"Miren","serverID":59,"guildID":1188,"contributionPoint":292993537,"memberCount":32,"masterName":"Reinholt","guildLevel":5,"soldierRankID":14,"raceID":0,"gloryPointChange":0},{"position":53,"arrowStatus":"STATIC","rankingPositionChange":1,"characterName":"Nariko","characterID":30383,"characterClassID":1,"gloryPoint":24020,"serverName":"Miren","serverID":59,"soldierRankID":14,"raceID":0,"gloryPointChange":450},{"position":54,"arrowStatus":"UP","rankingPositionChange":2,"characterName":"Kajlena","characterID":30387,"characterClassID":11,"gloryPoint":23848,"serverName":"Miren","serverID":59,"soldierRankID":14,"raceID":0,"gloryPointChange":540},{"position":55,"arrowStatus":"DOWN","rankingPositionChange":3,"characterName":"Aretuza","characterID":16455,"characterClassID":10,"gloryPoint":23774,"guildName":"  C H U L I G A N K A  ","serverName":"Miren","serverID":59,"guildID":1057,"contributionPoint":205754304,"memberCount":60,"masterName":"Ribon","guildLevel":6,"soldierRankID":14,"raceID":0,"gloryPointChange":900},{"position":56,"arrowStatus":"DOWN","rankingPositionChange":-3,"characterName":"Piremann","characterID":35709,"characterClassID":2,"gloryPoint":23627,"guildName":"  C H U L I G A N K A  ","serverName":"Miren","serverID":59,"guildID":1057,"contributionPoint":205754304,"memberCount":60,"masterName":"Ribon","guildLevel":6,"soldierRankID":14,"raceID":0,"gloryPointChange":0},{"position":57,"arrowStatus":"STATIC","rankingPositionChange":-2,"characterName":"Kiziamiziaa","characterID":38265,"characterClassID":5,"gloryPoint":23574,"guildName":"Angry Birds","serverName":"Miren","serverID":59,"guildID":1436,"contributionPoint":18996596,"memberCount":15,"masterName":"Hoshoshiro","guildLevel":4,"soldierRankID":14,"raceID":0,"gloryPointChange":111},{"position":58,"arrowStatus":"STATIC","rankingPositionChange":-1,"characterName":"Neiska","characterID":36913,"characterClassID":10,"gloryPoint":23075,"guildName":"Angry Birds","serverName":"Miren","serverID":59,"guildID":1436,"contributionPoint":18996596,"memberCount":15,"masterName":"Hoshoshiro","guildLevel":4,"soldierRankID":14,"raceID":0,"gloryPointChange":106},{"position":59,"arrowStatus":"STATIC","rankingPositionChange":0,"characterName":"Hoshoshiro","characterID":36914,"characterClassID":5,"gloryPoint":22432,"guildName":"Angry Birds","serverName":"Miren","serverID":59,"guildID":1436,"contributionPoint":18996596,"memberCount":15,"masterName":"Hoshoshiro","guildLevel":4,"soldierRankID":14,"raceID":0,"gloryPointChange":100},{"position":60,"arrowStatus":"STATIC","rankingPositionChange":0,"characterName":"Xeona","characterID":30401,"characterClassID":10,"gloryPoint":21146,"serverName":"Miren","serverID":59,"soldierRankID":14,"raceID":0,"gloryPointChange":690},{"position":61,"arrowStatus":"STATIC","rankingPositionChange":0,"characterName":"Pepita","characterID":35948,"characterClassID":10,"gloryPoint":21022,"serverName":"Miren","serverID":59,"soldierRankID":14,"raceID":0,"gloryPointChange":720},{"position":62,"arrowStatus":"STATIC","rankingPositionChange":0,"characterName":"Narico","characterID":30385,"characterClassID":11,"gloryPoint":20096,"serverName":"Miren","serverID":59,"soldierRankID":14,"raceID":0,"gloryPointChange":30},{"position":63,"arrowStatus":"UP","rankingPositionChange":1,"characterName":"Sophitia","characterID":30537,"characterClassID":8,"gloryPoint":18340,"serverName":"Miren","serverID":59,"soldierRankID":14,"raceID":0,"gloryPointChange":620},{"position":64,"arrowStatus":"DOWN","rankingPositionChange":-1,"characterName":"Cwaniak","characterID":45111,"characterClassID":4,"gloryPoint":18171,"guildName":"  C H U L I G A N K A  ","serverName":"Miren","serverID":59,"guildID":1057,"contributionPoint":205754304,"memberCount":60,"masterName":"Ribon","guildLevel":6,"soldierRankID":14,"raceID":0,"gloryPointChange":0},{"position":65,"arrowStatus":"STATIC","rankingPositionChange":0,"characterName":"Ramsey","characterID":22623,"characterClassID":10,"gloryPoint":15137,"guildName":"Hard Target","serverName":"Miren","serverID":59,"guildID":1408,"contributionPoint":5724089,"memberCount":4,"masterName":"Ramsey","guildLevel":2,"soldierRankID":14,"raceID":0,"gloryPointChange":0},{"position":66,"arrowStatus":"STATIC","rankingPositionChange":1,"characterName":"Mearia","characterID":42903,"characterClassID":1,"gloryPoint":13776,"guildName":"  C H U L I G A N K A  ","serverName":"Miren","serverID":59,"guildID":1057,"contributionPoint":205754304,"memberCount":60,"masterName":"Ribon","guildLevel":6,"soldierRankID":14,"raceID":0,"gloryPointChange":1315},{"position":67,"arrowStatus":"STATIC","rankingPositionChange":-1,"characterName":"Astarot","characterID":8751,"characterClassID":13,"gloryPoint":13121,"serverName":"Miren","serverID":59,"soldierRankID":14,"raceID":0,"gloryPointChange":50},{"position":68,"arrowStatus":"STATIC","rankingPositionChange":0,"characterName":"Leo","characterID":49418,"characterClassID":1,"gloryPoint":12754,"guildName":"MeTaL cLuB","serverName":"Miren","serverID":59,"guildID":1561,"contributionPoint":5292142,"memberCount":1,"masterName":"Leo","guildLevel":1,"soldierRankID":14,"raceID":0,"gloryPointChange":735},{"position":69,"arrowStatus":"STATIC","rankingPositionChange":0,"characterName":"Zabuza","characterID":9950,"characterClassID":5,"gloryPoint":11918,"guildName":"Nivis","serverName":"Miren","serverID":59,"guildID":1442,"contributionPoint":58436160,"memberCount":15,"masterName":"Leonik","guildLevel":5,"soldierRankID":14,"raceID":0,"gloryPointChange":0},{"position":70,"arrowStatus":"STATIC","rankingPositionChange":0,"characterName":"Martaa","characterID":22907,"characterClassID":11,"gloryPoint":10530,"guildName":"Sparta","serverName":"Miren","serverID":59,"guildID":1144,"contributionPoint":39323309,"memberCount":27,"masterName":"Anginsan","guildLevel":5,"soldierRankID":14,"raceID":0,"gloryPointChange":0},{"position":71,"arrowStatus":"STATIC","rankingPositionChange":0,"characterName":"Alamantheia","characterID":42445,"characterClassID":11,"gloryPoint":10417,"guildName":"FRIENDSHIP TEAM","serverName":"Miren","serverID":59,"guildID":1609,"contributionPoint":3289486,"memberCount":10,"masterName":"Blessstar","guildLevel":5,"soldierRankID":14,"raceID":0,"gloryPointChange":0},{"position":72,"arrowStatus":"STATIC","rankingPositionChange":0,"characterName":"Tornister","characterID":1606,"characterClassID":7,"gloryPoint":10006,"guildName":"Nivis","serverName":"Miren","serverID":59,"guildID":1442,"contributionPoint":58436160,"memberCount":15,"masterName":"Leonik","guildLevel":5,"soldierRankID":14,"raceID":0,"gloryPointChange":0},{"position":73,"arrowStatus":"STATIC","rankingPositionChange":0,"characterName":"Supersayan","characterID":16116,"characterClassID":8,"gloryPoint":9605,"guildName":"  C H U L I G A N K A  ","serverName":"Miren","serverID":59,"guildID":1057,"contributionPoint":205754304,"memberCount":60,"masterName":"Ribon","guildLevel":6,"soldierRankID":14,"raceID":0,"gloryPointChange":0},{"position":74,"arrowStatus":"STATIC","rankingPositionChange":0,"characterName":"Alida","characterID":43656,"characterClassID":2,"gloryPoint":9589,"guildName":"  C H U L I G A N K A  ","serverName":"Miren","serverID":59,"guildID":1057,"contributionPoint":205754304,"memberCount":60,"masterName":"Ribon","guildLevel":6,"soldierRankID":14,"raceID":0,"gloryPointChange":0},{"position":75,"arrowStatus":"STATIC","rankingPositionChange":0,"characterName":"Przemyslaw","characterID":5370,"characterClassID":16,"gloryPoint":8613,"guildName":"Nivis","serverName":"Miren","serverID":59,"guildID":1442,"contributionPoint":58436160,"memberCount":15,"masterName":"Leonik","guildLevel":5,"soldierRankID":14,"raceID":0,"gloryPointChange":0},{"position":76,"arrowStatus":"UP","rankingPositionChange":1,"characterName":"Deadlyarrow","characterID":51671,"characterClassID":5,"gloryPoint":7905,"guildName":"Hades","serverName":"Miren","serverID":59,"guildID":1584,"contributionPoint":3111960,"memberCount":8,"masterName":"Deadlyarrow","guildLevel":5,"soldierRankID":14,"raceID":0,"gloryPointChange":1425},{"position":77,"arrowStatus":"DOWN","rankingPositionChange":-1,"characterName":"Florin","characterID":45915,"characterClassID":8,"gloryPoint":7566,"guildName":"  C H U L I G A N K A  ","serverName":"Miren","serverID":59,"guildID":1057,"contributionPoint":205754304,"memberCount":60,"masterName":"Ribon","guildLevel":6,"soldierRankID":14,"raceID":0,"gloryPointChange":0},{"position":78,"arrowStatus":"STATIC","rankingPositionChange":0,"characterName":"Rayth","characterID":10373,"characterClassID":14,"gloryPoint":6230,"guildName":"Reapurrs","serverName":"Miren","serverID":59,"guildID":1031,"contributionPoint":5905231,"memberCount":2,"masterName":"Rayth","guildLevel":1,"soldierRankID":14,"raceID":0,"gloryPointChange":0},{"position":79,"arrowStatus":"STATIC","rankingPositionChange":1,"characterName":"Sebasu","characterID":50081,"characterClassID":1,"gloryPoint":6164,"serverName":"Miren","serverID":59,"soldierRankID":14,"raceID":0,"gloryPointChange":390},{"position":80,"arrowStatus":"STATIC","rankingPositionChange":-1,"characterName":"Kordiasu","characterID":50111,"characterClassID":2,"gloryPoint":6072,"serverName":"Miren","serverID":59,"soldierRankID":14,"raceID":0,"gloryPointChange":180},{"position":81,"arrowStatus":"STATIC","rankingPositionChange":0,"characterName":"Hardstyle","characterID":26800,"characterClassID":4,"gloryPoint":5832,"guildName":"FRIENDSHIP TEAM","serverName":"Miren","serverID":59,"guildID":1609,"contributionPoint":3289486,"memberCount":10,"masterName":"Blessstar","guildLevel":5,"soldierRankID":14,"raceID":0,"gloryPointChange":58},{"position":82,"arrowStatus":"STATIC","rankingPositionChange":1,"characterName":"Amarylis","characterID":30402,"characterClassID":14,"gloryPoint":5621,"serverName":"Miren","serverID":59,"soldierRankID":14,"raceID":0,"gloryPointChange":560},{"position":83,"arrowStatus":"UP","rankingPositionChange":1,"characterName":"Kaileena","characterID":30389,"characterClassID":8,"gloryPoint":5395,"serverName":"Miren","serverID":59,"soldierRankID":14,"raceID":0,"gloryPointChange":360},{"position":84,"arrowStatus":"DOWN","rankingPositionChange":-2,"characterName":"Mazen","characterID":40472,"characterClassID":16,"gloryPoint":5344,"guildName":"InVictus","serverName":"Miren","serverID":59,"guildID":1251,"contributionPoint":49997091,"memberCount":19,"masterName":"Mazen","guildLevel":6,"soldierRankID":14,"raceID":0,"gloryPointChange":12},{"position":85,"arrowStatus":"STATIC","rankingPositionChange":0,"characterName":"Myciu","characterID":47787,"characterClassID":4,"gloryPoint":4740,"guildName":"Warmasters","serverName":"Miren","serverID":59,"guildID":1503,"contributionPoint":14655834,"memberCount":62,"masterName":"Piast","guildLevel":5,"soldierRankID":13,"raceID":0,"gloryPointChange":370},{"position":86,"arrowStatus":"STATIC","rankingPositionChange":0,"characterName":"Aluk","characterID":46457,"characterClassID":10,"gloryPoint":4605,"guildName":"Warmasters","serverName":"Miren","serverID":59,"guildID":1503,"contributionPoint":14655834,"memberCount":62,"masterName":"Piast","guildLevel":5,"soldierRankID":13,"raceID":0,"gloryPointChange":600},{"position":87,"arrowStatus":"STATIC","rankingPositionChange":0,"characterName":"Ksienia","characterID":48688,"characterClassID":10,"gloryPoint":4023,"guildName":"Fearless","serverName":"Miren","serverID":59,"guildID":1036,"contributionPoint":231268699,"memberCount":87,"masterName":"Maniek","guildLevel":5,"soldierRankID":13,"raceID":0,"gloryPointChange":320},{"position":88,"arrowStatus":"STATIC","rankingPositionChange":0,"characterName":"Hilka","characterID":42823,"characterClassID":16,"gloryPoint":3369,"guildName":"Warmasters","serverName":"Miren","serverID":59,"guildID":1503,"contributionPoint":14655834,"memberCount":62,"masterName":"Piast","guildLevel":5,"soldierRankID":13,"raceID":0,"gloryPointChange":429},{"position":89,"arrowStatus":"STATIC","rankingPositionChange":0,"characterName":"Tiv","characterID":51387,"characterClassID":5,"gloryPoint":2778,"guildName":"InVictus","serverName":"Miren","serverID":59,"guildID":1251,"contributionPoint":49997091,"memberCount":19,"masterName":"Mazen","guildLevel":6,"soldierRankID":12,"raceID":0,"gloryPointChange":203},{"position":90,"arrowStatus":"UP","rankingPositionChange":1,"characterName":"Perfecta","characterID":39951,"characterClassID":10,"gloryPoint":2610,"guildName":"  C H U L I G A N K A  ","serverName":"Miren","serverID":59,"guildID":1057,"contributionPoint":205754304,"memberCount":60,"masterName":"Ribon","guildLevel":6,"soldierRankID":12,"raceID":0,"gloryPointChange":450},{"position":91,"arrowStatus":"DOWN","rankingPositionChange":-1,"characterName":"Targhar","characterID":44816,"characterClassID":8,"gloryPoint":2373,"guildName":"Warmasters","serverName":"Miren","serverID":59,"guildID":1503,"contributionPoint":14655834,"memberCount":62,"masterName":"Piast","guildLevel":5,"soldierRankID":12,"raceID":0,"gloryPointChange":0},{"position":92,"arrowStatus":"DOWN","rankingPositionChange":0,"characterName":"Pmg","characterID":53088,"characterClassID":5,"gloryPoint":2315,"guildName":"Fearless","serverName":"Miren","serverID":59,"guildID":1036,"contributionPoint":231268699,"memberCount":87,"masterName":"Maniek","guildLevel":5,"soldierRankID":12,"raceID":0,"gloryPointChange":250},{"position":93,"arrowStatus":"STATIC","rankingPositionChange":0,"characterName":"Midjacek","characterID":47445,"characterClassID":5,"gloryPoint":2175,"serverName":"Miren","serverID":59,"soldierRankID":12,"raceID":0,"gloryPointChange":350},{"position":94,"arrowStatus":"STATIC","rankingPositionChange":0,"characterName":"Aakashi","characterID":50158,"characterClassID":1,"gloryPoint":2008,"serverName":"Miren","serverID":59,"soldierRankID":12,"raceID":0,"gloryPointChange":0},{"position":95,"arrowStatus":"DOWN","rankingPositionChange":-1,"characterName":"Piastowa","characterID":42689,"characterClassID":16,"gloryPoint":1715,"guildName":"Warmasters","serverName":"Miren","serverID":59,"guildID":1503,"contributionPoint":14655834,"memberCount":62,"masterName":"Piast","guildLevel":5,"soldierRankID":11,"raceID":0,"gloryPointChange":0},{"position":96,"arrowStatus":"DOWN","rankingPositionChange":-1,"characterName":"Vladus","characterID":46352,"characterClassID":10,"gloryPoint":1714,"guildName":"InVictus","serverName":"Miren","serverID":59,"guildID":1251,"contributionPoint":49997091,"memberCount":19,"masterName":"Mazen","guildLevel":6,"soldierRankID":11,"raceID":0,"gloryPointChange":0}],"asmodians":[{"position":1,"arrowStatus":"STATIC","rankingPositionChange":0,"characterName":"Lordsm","characterID":4496,"characterClassID":8,"gloryPoint":291112,"guildName":"Pathology Squad","serverName":"Miren","serverID":59,"guildID":1096,"contributionPoint":187735467,"memberCount":35,"masterName":"Lordsm","guildLevel":6,"soldierRankID":18,"raceID":1,"gloryPointChange":4106},{"position":2,"arrowStatus":"STATIC","rankingPositionChange":0,"characterName":"Cossmo","characterID":1445,"characterClassID":7,"gloryPoint":284859,"guildName":"Genocide","serverName":"Miren","serverID":59,"guildID":1007,"contributionPoint":651734565,"memberCount":25,"masterName":"Dargor","guildLevel":6,"soldierRankID":17,"raceID":1,"gloryPointChange":2081},{"position":3,"arrowStatus":"STATIC","rankingPositionChange":0,"characterName":"Terion","characterID":1361,"characterClassID":2,"gloryPoint":284079,"serverName":"Miren","serverID":59,"soldierRankID":17,"raceID":1,"gloryPointChange":5396},{"position":4,"arrowStatus":"STATIC","rankingPositionChange":0,"characterName":"Shisu","characterID":18444,"characterClassID":16,"gloryPoint":259889,"guildName":"Genocide","serverName":"Miren","serverID":59,"guildID":1007,"contributionPoint":651734565,"memberCount":25,"masterName":"Dargor","guildLevel":6,"soldierRankID":16,"raceID":1,"gloryPointChange":0},{"position":5,"arrowStatus":"STATIC","rankingPositionChange":0,"characterName":"Rannva","characterID":1130,"characterClassID":10,"gloryPoint":244702,"guildName":"Fantasy","serverName":"Miren","serverID":59,"guildID":1195,"contributionPoint":458337364,"memberCount":19,"masterName":"Livo","guildLevel":5,"soldierRankID":16,"raceID":1,"gloryPointChange":4502},{"position":6,"arrowStatus":"STATIC","rankingPositionChange":0,"characterName":"Gje","characterID":1092,"characterClassID":11,"gloryPoint":236525,"guildName":"Fantasy","serverName":"Miren","serverID":59,"guildID":1195,"contributionPoint":458337364,"memberCount":19,"masterName":"Livo","guildLevel":5,"soldierRankID":16,"raceID":1,"gloryPointChange":4335},{"position":7,"arrowStatus":"STATIC","rankingPositionChange":0,"characterName":"Gronek","characterID":1593,"characterClassID":5,"gloryPoint":223814,"guildName":"Ekipa Remontowa","serverName":"Miren","serverID":59,"guildID":1009,"contributionPoint":211616763,"memberCount":8,"masterName":"Gronek","guildLevel":5,"soldierRankID":16,"raceID":1,"gloryPointChange":900},{"position":8,"arrowStatus":"STATIC","rankingPositionChange":0,"characterName":"Xclusives","characterID":2724,"characterClassID":11,"gloryPoint":222585,"guildName":"Veni Vidi Vici","serverName":"Miren","serverID":59,"guildID":1278,"contributionPoint":41011150,"memberCount":25,"masterName":"Xclusives","guildLevel":5,"soldierRankID":16,"raceID":1,"gloryPointChange":2307},{"position":9,"arrowStatus":"STATIC","rankingPositionChange":0,"characterName":"Fushinka","characterID":27840,"characterClassID":10,"gloryPoint":217707,"guildName":" Strangers ","serverName":"Miren","serverID":59,"guildID":1516,"contributionPoint":62931896,"memberCount":13,"masterName":"Fushinka","guildLevel":5,"soldierRankID":16,"raceID":1,"gloryPointChange":10272},{"position":10,"arrowStatus":"STATIC","rankingPositionChange":1,"characterName":"Maczeta","characterID":8359,"characterClassID":13,"gloryPoint":210087,"guildName":"Muminki","serverName":"Miren","serverID":59,"guildID":1358,"contributionPoint":13469505,"memberCount":8,"masterName":"Disney","guildLevel":5,"soldierRankID":16,"raceID":1,"gloryPointChange":4943},{"position":11,"arrowStatus":"STATIC","rankingPositionChange":-1,"characterName":"Chrumka","characterID":2354,"characterClassID":11,"gloryPoint":209112,"guildName":"Genocide","serverName":"Miren","serverID":59,"guildID":1007,"contributionPoint":651734565,"memberCount":25,"masterName":"Dargor","guildLevel":6,"soldierRankID":15,"raceID":1,"gloryPointChange":2321},{"position":12,"arrowStatus":"STATIC","rankingPositionChange":0,"characterName":"Roche","characterID":1020,"characterClassID":16,"gloryPoint":208516,"guildName":"Pathology Squad","serverName":"Miren","serverID":59,"guildID":1096,"contributionPoint":187735467,"memberCount":35,"masterName":"Lordsm","guildLevel":6,"soldierRankID":15,"raceID":1,"gloryPointChange":5802},{"position":13,"arrowStatus":"STATIC","rankingPositionChange":1,"characterName":"Myobsession","characterID":13652,"characterClassID":1,"gloryPoint":196175,"guildName":"Genocide","serverName":"Miren","serverID":59,"guildID":1007,"contributionPoint":651734565,"memberCount":25,"masterName":"Dargor","guildLevel":6,"soldierRankID":15,"raceID":1,"gloryPointChange":4119},{"position":14,"arrowStatus":"STATIC","rankingPositionChange":-1,"characterName":"Mats","characterID":18434,"characterClassID":5,"gloryPoint":195112,"guildName":"Fantasy","serverName":"Miren","serverID":59,"guildID":1195,"contributionPoint":458337364,"memberCount":19,"masterName":"Livo","guildLevel":5,"soldierRankID":15,"raceID":1,"gloryPointChange":1498},{"position":15,"arrowStatus":"UP","rankingPositionChange":2,"characterName":"Kanade","characterID":17685,"characterClassID":2,"gloryPoint":193776,"guildName":" Strangers ","serverName":"Miren","serverID":59,"guildID":1516,"contributionPoint":62931896,"memberCount":13,"masterName":"Fushinka","guildLevel":5,"soldierRankID":15,"raceID":1,"gloryPointChange":11014},{"position":16,"arrowStatus":"DOWN","rankingPositionChange":-1,"characterName":"Nesima","characterID":1535,"characterClassID":10,"gloryPoint":191448,"guildName":"Ekipa Remontowa","serverName":"Miren","serverID":59,"guildID":1009,"contributionPoint":211616763,"memberCount":8,"masterName":"Gronek","guildLevel":5,"soldierRankID":15,"raceID":1,"gloryPointChange":900},{"position":17,"arrowStatus":"DOWN","rankingPositionChange":-1,"characterName":"Zirah","characterID":1752,"characterClassID":10,"gloryPoint":188713,"guildName":"Pathology Squad","serverName":"Miren","serverID":59,"guildID":1096,"contributionPoint":187735467,"memberCount":35,"masterName":"Lordsm","guildLevel":6,"soldierRankID":15,"raceID":1,"gloryPointChange":1950},{"position":18,"arrowStatus":"STATIC","rankingPositionChange":0,"characterName":"Wega","characterID":1434,"characterClassID":10,"gloryPoint":184812,"guildName":"Genocide","serverName":"Miren","serverID":59,"guildID":1007,"contributionPoint":651734565,"memberCount":25,"masterName":"Dargor","guildLevel":6,"soldierRankID":15,"raceID":1,"gloryPointChange":2150},{"position":19,"arrowStatus":"UP","rankingPositionChange":3,"characterName":"Gryf","characterID":40582,"characterClassID":1,"gloryPoint":183560,"guildName":" Strangers ","serverName":"Miren","serverID":59,"guildID":1516,"contributionPoint":62931896,"memberCount":13,"masterName":"Fushinka","guildLevel":5,"soldierRankID":15,"raceID":1,"gloryPointChange":10354},{"position":20,"arrowStatus":"DOWN","rankingPositionChange":-1,"characterName":"Scream","characterID":7078,"characterClassID":8,"gloryPoint":182061,"guildName":"Veni Vidi Vici","serverName":"Miren","serverID":59,"guildID":1278,"contributionPoint":41011150,"memberCount":25,"masterName":"Xclusives","guildLevel":5,"soldierRankID":15,"raceID":1,"gloryPointChange":3232},{"position":21,"arrowStatus":"DOWN","rankingPositionChange":-1,"characterName":"Ojej","characterID":8975,"characterClassID":5,"gloryPoint":180775,"guildName":"Genocide","serverName":"Miren","serverID":59,"guildID":1007,"contributionPoint":651734565,"memberCount":25,"masterName":"Dargor","guildLevel":6,"soldierRankID":15,"raceID":1,"gloryPointChange":4144},{"position":22,"arrowStatus":"STATIC","rankingPositionChange":-1,"characterName":"Haku","characterID":1220,"characterClassID":14,"gloryPoint":174711,"guildName":"Pathology Squad","serverName":"Miren","serverID":59,"guildID":1096,"contributionPoint":187735467,"memberCount":35,"masterName":"Lordsm","guildLevel":6,"soldierRankID":15,"raceID":1,"gloryPointChange":0},{"position":23,"arrowStatus":"STATIC","rankingPositionChange":0,"characterName":"Flonne","characterID":2010,"characterClassID":16,"gloryPoint":172691,"serverName":"Miren","serverID":59,"soldierRankID":15,"raceID":1,"gloryPointChange":2210},{"position":24,"arrowStatus":"STATIC","rankingPositionChange":0,"characterName":"Sneak","characterID":18726,"characterClassID":11,"gloryPoint":170015,"guildName":"Fantasy","serverName":"Miren","serverID":59,"guildID":1195,"contributionPoint":458337364,"memberCount":19,"masterName":"Livo","guildLevel":5,"soldierRankID":15,"raceID":1,"gloryPointChange":1347},{"position":25,"arrowStatus":"STATIC","rankingPositionChange":0,"characterName":"Avengerx","characterID":12959,"characterClassID":13,"gloryPoint":169874,"guildName":"Genocide","serverName":"Miren","serverID":59,"guildID":1007,"contributionPoint":651734565,"memberCount":25,"masterName":"Dargor","guildLevel":6,"soldierRankID":15,"raceID":1,"gloryPointChange":3194},{"position":26,"arrowStatus":"STATIC","rankingPositionChange":0,"characterName":"Trixe","characterID":18400,"characterClassID":10,"gloryPoint":166791,"guildName":"Fantasy","serverName":"Miren","serverID":59,"guildID":1195,"contributionPoint":458337364,"memberCount":19,"masterName":"Livo","guildLevel":5,"soldierRankID":15,"raceID":1,"gloryPointChange":2584},{"position":27,"arrowStatus":"UP","rankingPositionChange":1,"characterName":"Krewet","characterID":2226,"characterClassID":11,"gloryPoint":158741,"guildName":"Genocide","serverName":"Miren","serverID":59,"guildID":1007,"contributionPoint":651734565,"memberCount":25,"masterName":"Dargor","guildLevel":6,"soldierRankID":15,"raceID":1,"gloryPointChange":2841},{"position":28,"arrowStatus":"UP","rankingPositionChange":3,"characterName":"Azraiel","characterID":42403,"characterClassID":11,"gloryPoint":157277,"guildName":" Strangers ","serverName":"Miren","serverID":59,"guildID":1516,"contributionPoint":62931896,"memberCount":13,"masterName":"Fushinka","guildLevel":5,"soldierRankID":15,"raceID":1,"gloryPointChange":6452},{"position":29,"arrowStatus":"DOWN","rankingPositionChange":-2,"characterName":"Casadris","characterID":2207,"characterClassID":10,"gloryPoint":156787,"guildName":"Genocide","serverName":"Miren","serverID":59,"guildID":1007,"contributionPoint":651734565,"memberCount":25,"masterName":"Dargor","guildLevel":6,"soldierRankID":15,"raceID":1,"gloryPointChange":0},{"position":30,"arrowStatus":"UP","rankingPositionChange":2,"characterName":"Tygry","characterID":1835,"characterClassID":16,"gloryPoint":156039,"guildName":"DevastatioN","serverName":"Miren","serverID":59,"guildID":1033,"contributionPoint":267084594,"memberCount":22,"masterName":"Fuxy","guildLevel":5,"soldierRankID":15,"raceID":1,"gloryPointChange":5783},{"position":31,"arrowStatus":"UP","rankingPositionChange":-1,"characterName":"Kornik","characterID":11799,"characterClassID":16,"gloryPoint":155348,"guildName":"Fantasy","serverName":"Miren","serverID":59,"guildID":1195,"contributionPoint":458337364,"memberCount":19,"masterName":"Livo","guildLevel":5,"soldierRankID":14,"raceID":1,"gloryPointChange":1071},{"position":32,"arrowStatus":"DOWN","rankingPositionChange":-3,"characterName":"Firely","characterID":1122,"characterClassID":7,"gloryPoint":154976,"serverName":"Miren","serverID":59,"soldierRankID":14,"raceID":1,"gloryPointChange":303},{"position":33,"arrowStatus":"STATIC","rankingPositionChange":0,"characterName":"Morketia","characterID":8453,"characterClassID":10,"gloryPoint":151195,"guildName":"Easy","serverName":"Miren","serverID":59,"guildID":1338,"contributionPoint":54216054,"memberCount":26,"masterName":"Donor","guildLevel":5,"soldierRankID":14,"raceID":1,"gloryPointChange":4150},{"position":34,"arrowStatus":"STATIC","rankingPositionChange":1,"characterName":"Setesh","characterID":18403,"characterClassID":10,"gloryPoint":147861,"guildName":"Fantasy","serverName":"Miren","serverID":59,"guildID":1195,"contributionPoint":458337364,"memberCount":19,"masterName":"Livo","guildLevel":5,"soldierRankID":14,"raceID":1,"gloryPointChange":5007},{"position":35,"arrowStatus":"STATIC","rankingPositionChange":-1,"characterName":"Rvik","characterID":2266,"characterClassID":1,"gloryPoint":142959,"guildName":"DevastatioN","serverName":"Miren","serverID":59,"guildID":1033,"contributionPoint":267084594,"memberCount":22,"masterName":"Fuxy","guildLevel":5,"soldierRankID":14,"raceID":1,"gloryPointChange":0},{"position":36,"arrowStatus":"UP","rankingPositionChange":1,"characterName":"Berry","characterID":18156,"characterClassID":8,"gloryPoint":140059,"guildName":"Fantasy","serverName":"Miren","serverID":59,"guildID":1195,"contributionPoint":458337364,"memberCount":19,"masterName":"Livo","guildLevel":5,"soldierRankID":14,"raceID":1,"gloryPointChange":1410},{"position":37,"arrowStatus":"DOWN","rankingPositionChange":-1,"characterName":"Yate","characterID":1173,"characterClassID":1,"gloryPoint":139714,"guildName":"Genocide","serverName":"Miren","serverID":59,"guildID":1007,"contributionPoint":651734565,"memberCount":25,"masterName":"Dargor","guildLevel":6,"soldierRankID":14,"raceID":1,"gloryPointChange":0},{"position":38,"arrowStatus":"STATIC","rankingPositionChange":0,"characterName":"Furcek","characterID":3261,"characterClassID":10,"gloryPoint":135190,"guildName":"OgarNIEmy","serverName":"Miren","serverID":59,"guildID":1277,"contributionPoint":16970844,"memberCount":11,"masterName":"Furcek","guildLevel":6,"soldierRankID":14,"raceID":1,"gloryPointChange":0},{"position":39,"arrowStatus":"STATIC","rankingPositionChange":0,"characterName":"Neko","characterID":1037,"characterClassID":13,"gloryPoint":132970,"serverName":"Miren","serverID":59,"soldierRankID":14,"raceID":1,"gloryPointChange":0},{"position":40,"arrowStatus":"STATIC","rankingPositionChange":0,"characterName":"Suren","characterID":5439,"characterClassID":16,"gloryPoint":127478,"guildName":"Tartaros","serverName":"Miren","serverID":59,"guildID":1047,"contributionPoint":107752451,"memberCount":51,"masterName":"Mijarane","guildLevel":6,"soldierRankID":14,"raceID":1,"gloryPointChange":3823},{"position":41,"arrowStatus":"STATIC","rankingPositionChange":1,"characterName":"Fuxy","characterID":2441,"characterClassID":16,"gloryPoint":121665,"guildName":"DevastatioN","serverName":"Miren","serverID":59,"guildID":1033,"contributionPoint":267084594,"memberCount":22,"masterName":"Fuxy","guildLevel":5,"soldierRankID":14,"raceID":1,"gloryPointChange":3866},{"position":42,"arrowStatus":"STATIC","rankingPositionChange":1,"characterName":"Dexti","characterID":21705,"characterClassID":1,"gloryPoint":119487,"guildName":"Genocide","serverName":"Miren","serverID":59,"guildID":1007,"contributionPoint":651734565,"memberCount":25,"masterName":"Dargor","guildLevel":6,"soldierRankID":14,"raceID":1,"gloryPointChange":1760},{"position":43,"arrowStatus":"STATIC","rankingPositionChange":-2,"characterName":"Roou","characterID":2496,"characterClassID":4,"gloryPoint":119442,"guildName":"Veni Vidi Vici","serverName":"Miren","serverID":59,"guildID":1278,"contributionPoint":41011150,"memberCount":25,"masterName":"Xclusives","guildLevel":5,"soldierRankID":14,"raceID":1,"gloryPointChange":0},{"position":44,"arrowStatus":"STATIC","rankingPositionChange":0,"characterName":"Sziszu","characterID":3801,"characterClassID":2,"gloryPoint":116451,"guildName":"Porzadny Dupek","serverName":"Miren","serverID":59,"guildID":1395,"contributionPoint":5720557,"memberCount":3,"masterName":"Sziszu","guildLevel":1,"soldierRankID":14,"raceID":1,"gloryPointChange":0},{"position":45,"arrowStatus":"STATIC","rankingPositionChange":0,"characterName":"Dargor","characterID":9506,"characterClassID":14,"gloryPoint":114927,"guildName":"Genocide","serverName":"Miren","serverID":59,"guildID":1007,"contributionPoint":651734565,"memberCount":25,"masterName":"Dargor","guildLevel":6,"soldierRankID":14,"raceID":1,"gloryPointChange":3884},{"position":46,"arrowStatus":"STATIC","rankingPositionChange":1,"characterName":"Muya","characterID":1594,"characterClassID":1,"gloryPoint":112492,"guildName":"LEGENDARNI","serverName":"Miren","serverID":59,"guildID":1567,"contributionPoint":24311790,"memberCount":30,"masterName":"Fellentia","guildLevel":5,"soldierRankID":14,"raceID":1,"gloryPointChange":3858},{"position":47,"arrowStatus":"STATIC","rankingPositionChange":1,"characterName":"Pisa","characterID":2138,"characterClassID":7,"gloryPoint":112183,"guildName":"Tartaros","serverName":"Miren","serverID":59,"guildID":1047,"contributionPoint":107752451,"memberCount":51,"masterName":"Mijarane","guildLevel":6,"soldierRankID":14,"raceID":1,"gloryPointChange":4266},{"position":48,"arrowStatus":"UP","rankingPositionChange":1,"characterName":"Kaidan","characterID":1609,"characterClassID":7,"gloryPoint":110474,"guildName":" Infinity Cookies ","serverName":"Miren","serverID":59,"guildID":1571,"contributionPoint":15792595,"memberCount":26,"masterName":"Zick","guildLevel":5,"soldierRankID":14,"raceID":1,"gloryPointChange":3050},{"position":49,"arrowStatus":"DOWN","rankingPositionChange":-3,"characterName":"Lissa","characterID":1693,"characterClassID":10,"gloryPoint":109809,"serverName":"Miren","serverID":59,"soldierRankID":14,"raceID":1,"gloryPointChange":0},{"position":50,"arrowStatus":"UP","rankingPositionChange":2,"characterName":"Maruda","characterID":1057,"characterClassID":10,"gloryPoint":103116,"guildName":"Pathology Squad","serverName":"Miren","serverID":59,"guildID":1096,"contributionPoint":187735467,"memberCount":35,"masterName":"Lordsm","guildLevel":6,"soldierRankID":14,"raceID":1,"gloryPointChange":3948},{"position":51,"arrowStatus":"DOWN","rankingPositionChange":-1,"characterName":"Tigzor","characterID":19667,"characterClassID":1,"gloryPoint":102849,"guildName":"DevastatioN","serverName":"Miren","serverID":59,"guildID":1033,"contributionPoint":267084594,"memberCount":22,"masterName":"Fuxy","guildLevel":5,"soldierRankID":14,"raceID":1,"gloryPointChange":1517},{"position":52,"arrowStatus":"STATIC","rankingPositionChange":-1,"characterName":"Hired","characterID":1485,"characterClassID":11,"gloryPoint":102207,"guildName":"Ekipa Remontowa","serverName":"Miren","serverID":59,"guildID":1009,"contributionPoint":211616763,"memberCount":8,"masterName":"Gronek","guildLevel":5,"soldierRankID":14,"raceID":1,"gloryPointChange":1315},{"position":53,"arrowStatus":"STATIC","rankingPositionChange":1,"characterName":"Lettia","characterID":8454,"characterClassID":10,"gloryPoint":96450,"guildName":"Easy","serverName":"Miren","serverID":59,"guildID":1338,"contributionPoint":54216054,"memberCount":26,"masterName":"Donor","guildLevel":5,"soldierRankID":14,"raceID":1,"gloryPointChange":1760},{"position":54,"arrowStatus":"STATIC","rankingPositionChange":-1,"characterName":"Missandeii","characterID":21295,"characterClassID":5,"gloryPoint":96368,"guildName":"DevastatioN","serverName":"Miren","serverID":59,"guildID":1033,"contributionPoint":267084594,"memberCount":22,"masterName":"Fuxy","guildLevel":5,"soldierRankID":14,"raceID":1,"gloryPointChange":0},{"position":55,"arrowStatus":"STATIC","rankingPositionChange":1,"characterName":"Czarna","characterID":6352,"characterClassID":10,"gloryPoint":93405,"guildName":"Stray Dogs","serverName":"Miren","serverID":59,"guildID":1563,"contributionPoint":25315856,"memberCount":16,"masterName":"Shuuri","guildLevel":5,"soldierRankID":14,"raceID":1,"gloryPointChange":1820},{"position":56,"arrowStatus":"UP","rankingPositionChange":-1,"characterName":"Poyo","characterID":1466,"characterClassID":4,"gloryPoint":93139,"guildName":"Pathology Squad","serverName":"Miren","serverID":59,"guildID":1096,"contributionPoint":187735467,"memberCount":35,"masterName":"Lordsm","guildLevel":6,"soldierRankID":14,"raceID":1,"gloryPointChange":900},{"position":57,"arrowStatus":"DOWN","rankingPositionChange":1,"characterName":"Skydream","characterID":24861,"characterClassID":5,"gloryPoint":92433,"guildName":"Tartaros","serverName":"Miren","serverID":59,"guildID":1047,"contributionPoint":107752451,"memberCount":51,"masterName":"Mijarane","guildLevel":6,"soldierRankID":14,"raceID":1,"gloryPointChange":2312},{"position":58,"arrowStatus":"STATIC","rankingPositionChange":1,"characterName":"Stitcher","characterID":6620,"characterClassID":16,"gloryPoint":92040,"guildName":"Stray Dogs","serverName":"Miren","serverID":59,"guildID":1563,"contributionPoint":25315856,"memberCount":16,"masterName":"Shuuri","guildLevel":5,"soldierRankID":14,"raceID":1,"gloryPointChange":3050},{"position":59,"arrowStatus":"STATIC","rankingPositionChange":-2,"characterName":"Carllos","characterID":1257,"characterClassID":4,"gloryPoint":90329,"guildName":"DevastatioN","serverName":"Miren","serverID":59,"guildID":1033,"contributionPoint":267084594,"memberCount":22,"masterName":"Fuxy","guildLevel":5,"soldierRankID":14,"raceID":1,"gloryPointChange":0},{"position":60,"arrowStatus":"UP","rankingPositionChange":1,"characterName":"Asti","characterID":16555,"characterClassID":11,"gloryPoint":87594,"guildName":"Pathology Squad","serverName":"Miren","serverID":59,"guildID":1096,"contributionPoint":187735467,"memberCount":35,"masterName":"Lordsm","guildLevel":6,"soldierRankID":14,"raceID":1,"gloryPointChange":4051},{"position":61,"arrowStatus":"DOWN","rankingPositionChange":-1,"characterName":"Yadowita","characterID":5358,"characterClassID":5,"gloryPoint":86153,"guildName":"OgarNIEmy","serverName":"Miren","serverID":59,"guildID":1277,"contributionPoint":16970844,"memberCount":11,"masterName":"Furcek","guildLevel":6,"soldierRankID":14,"raceID":1,"gloryPointChange":540},{"position":62,"arrowStatus":"STATIC","rankingPositionChange":0,"characterName":"Casi","characterID":18822,"characterClassID":11,"gloryPoint":82776,"guildName":"Pathology Squad","serverName":"Miren","serverID":59,"guildID":1096,"contributionPoint":187735467,"memberCount":35,"masterName":"Lordsm","guildLevel":6,"soldierRankID":14,"raceID":1,"gloryPointChange":1290},{"position":63,"arrowStatus":"STATIC","rankingPositionChange":0,"characterName":"Yaoguai","characterID":11229,"characterClassID":16,"gloryPoint":82158,"guildName":"Pathology Squad","serverName":"Miren","serverID":59,"guildID":1096,"contributionPoint":187735467,"memberCount":35,"masterName":"Lordsm","guildLevel":6,"soldierRankID":14,"raceID":1,"gloryPointChange":950},{"position":64,"arrowStatus":"STATIC","rankingPositionChange":0,"characterName":"Leomi","characterID":12373,"characterClassID":7,"gloryPoint":81120,"serverName":"Miren","serverID":59,"soldierRankID":14,"raceID":1,"gloryPointChange":0},{"position":65,"arrowStatus":"STATIC","rankingPositionChange":0,"characterName":"Ariela","characterID":7165,"characterClassID":10,"gloryPoint":80757,"guildName":"Stray Dogs","serverName":"Miren","serverID":59,"guildID":1563,"contributionPoint":25315856,"memberCount":16,"masterName":"Shuuri","guildLevel":5,"soldierRankID":14,"raceID":1,"gloryPointChange":2850},{"position":66,"arrowStatus":"STATIC","rankingPositionChange":0,"characterName":"Elsors","characterID":2456,"characterClassID":1,"gloryPoint":79436,"guildName":"Tartaros","serverName":"Miren","serverID":59,"guildID":1047,"contributionPoint":107752451,"memberCount":51,"masterName":"Mijarane","guildLevel":6,"soldierRankID":14,"raceID":1,"gloryPointChange":3423},{"position":67,"arrowStatus":"STATIC","rankingPositionChange":1,"characterName":"Lorii","characterID":9559,"characterClassID":10,"gloryPoint":78384,"guildName":"LEGENDARNI","serverName":"Miren","serverID":59,"guildID":1567,"contributionPoint":24311790,"memberCount":30,"masterName":"Fellentia","guildLevel":5,"soldierRankID":14,"raceID":1,"gloryPointChange":4015},{"position":68,"arrowStatus":"STATIC","rankingPositionChange":1,"characterName":"Kaname","characterID":9326,"characterClassID":16,"gloryPoint":77111,"serverName":"Miren","serverID":59,"soldierRankID":14,"raceID":1,"gloryPointChange":2840},{"position":69,"arrowStatus":"UP","rankingPositionChange":1,"characterName":"Pinnacle","characterID":3122,"characterClassID":2,"gloryPoint":75798,"serverName":"Miren","serverID":59,"soldierRankID":14,"raceID":1,"gloryPointChange":1785},{"position":70,"arrowStatus":"DOWN","rankingPositionChange":-3,"characterName":"Yamaki","characterID":24557,"characterClassID":10,"gloryPoint":74498,"guildName":"Veni Vidi Vici","serverName":"Miren","serverID":59,"guildID":1278,"contributionPoint":41011150,"memberCount":25,"masterName":"Xclusives","guildLevel":5,"soldierRankID":14,"raceID":1,"gloryPointChange":0},{"position":71,"arrowStatus":"STATIC","rankingPositionChange":0,"characterName":"Miau","characterID":7402,"characterClassID":10,"gloryPoint":73468,"guildName":"Genocide","serverName":"Miren","serverID":59,"guildID":1007,"contributionPoint":651734565,"memberCount":25,"masterName":"Dargor","guildLevel":6,"soldierRankID":14,"raceID":1,"gloryPointChange":0},{"position":72,"arrowStatus":"STATIC","rankingPositionChange":0,"characterName":"Three","characterID":12705,"characterClassID":5,"gloryPoint":72912,"serverName":"Miren","serverID":59,"soldierRankID":14,"raceID":1,"gloryPointChange":0},{"position":73,"arrowStatus":"STATIC","rankingPositionChange":0,"characterName":"Wakos","characterID":4712,"characterClassID":2,"gloryPoint":72676,"guildName":"Veni Vidi Vici","serverName":"Miren","serverID":59,"guildID":1278,"contributionPoint":41011150,"memberCount":25,"masterName":"Xclusives","guildLevel":5,"soldierRankID":14,"raceID":1,"gloryPointChange":0},{"position":74,"arrowStatus":"STATIC","rankingPositionChange":0,"characterName":"Ksiundz","characterID":15246,"characterClassID":10,"gloryPoint":71535,"guildName":" Infinity Cookies ","serverName":"Miren","serverID":59,"guildID":1571,"contributionPoint":15792595,"memberCount":26,"masterName":"Zick","guildLevel":5,"soldierRankID":14,"raceID":1,"gloryPointChange":180},{"position":75,"arrowStatus":"UP","rankingPositionChange":2,"characterName":"Morgar","characterID":1740,"characterClassID":11,"gloryPoint":71450,"guildName":" Infinity Cookies ","serverName":"Miren","serverID":59,"guildID":1571,"contributionPoint":15792595,"memberCount":26,"masterName":"Zick","guildLevel":5,"soldierRankID":14,"raceID":1,"gloryPointChange":2850},{"position":76,"arrowStatus":"DOWN","rankingPositionChange":-1,"characterName":"Szogunnnxx","characterID":20499,"characterClassID":2,"gloryPoint":70847,"guildName":"Stray Dogs","serverName":"Miren","serverID":59,"guildID":1563,"contributionPoint":25315856,"memberCount":16,"masterName":"Shuuri","guildLevel":5,"soldierRankID":14,"raceID":1,"gloryPointChange":75},{"position":77,"arrowStatus":"STATIC","rankingPositionChange":-1,"characterName":"Gargi","characterID":5615,"characterClassID":5,"gloryPoint":70336,"guildName":"Shadows","serverName":"Miren","serverID":59,"guildID":1345,"contributionPoint":26828936,"memberCount":24,"masterName":"Gargi","guildLevel":5,"soldierRankID":14,"raceID":1,"gloryPointChange":0},{"position":78,"arrowStatus":"UP","rankingPositionChange":1,"characterName":"Armandi","characterID":21993,"characterClassID":16,"gloryPoint":69327,"guildName":"Tartaros","serverName":"Miren","serverID":59,"guildID":1047,"contributionPoint":107752451,"memberCount":51,"masterName":"Mijarane","guildLevel":6,"soldierRankID":14,"raceID":1,"gloryPointChange":2850},{"position":79,"arrowStatus":"DOWN","rankingPositionChange":-1,"characterName":"Amharra","characterID":2986,"characterClassID":1,"gloryPoint":68443,"guildName":"Stray Dogs","serverName":"Miren","serverID":59,"guildID":1563,"contributionPoint":25315856,"memberCount":16,"masterName":"Shuuri","guildLevel":5,"soldierRankID":14,"raceID":1,"gloryPointChange":0},{"position":80,"arrowStatus":"STATIC","rankingPositionChange":0,"characterName":"Salemus","characterID":20151,"characterClassID":7,"gloryPoint":63888,"guildName":"Stray Dogs","serverName":"Miren","serverID":59,"guildID":1563,"contributionPoint":25315856,"memberCount":16,"masterName":"Shuuri","guildLevel":5,"soldierRankID":14,"raceID":1,"gloryPointChange":2245},{"position":81,"arrowStatus":"STATIC","rankingPositionChange":0,"characterName":"Asteria","characterID":28117,"characterClassID":1,"gloryPoint":62314,"guildName":" Infinity Cookies ","serverName":"Miren","serverID":59,"guildID":1571,"contributionPoint":15792595,"memberCount":26,"masterName":"Zick","guildLevel":5,"soldierRankID":14,"raceID":1,"gloryPointChange":2660},{"position":82,"arrowStatus":"STATIC","rankingPositionChange":0,"characterName":"Donor","characterID":16293,"characterClassID":16,"gloryPoint":61418,"guildName":"Easy","serverName":"Miren","serverID":59,"guildID":1338,"contributionPoint":54216054,"memberCount":26,"masterName":"Donor","guildLevel":5,"soldierRankID":14,"raceID":1,"gloryPointChange":2000},{"position":83,"arrowStatus":"STATIC","rankingPositionChange":4,"characterName":"Sanerty","characterID":27524,"characterClassID":16,"gloryPoint":59853,"guildName":" Infinity Cookies ","serverName":"Miren","serverID":59,"guildID":1571,"contributionPoint":15792595,"memberCount":26,"masterName":"Zick","guildLevel":5,"soldierRankID":14,"raceID":1,"gloryPointChange":3085},{"position":84,"arrowStatus":"UP","rankingPositionChange":0,"characterName":"Broda","characterID":39285,"characterClassID":10,"gloryPoint":59107,"guildName":"Tartaros","serverName":"Miren","serverID":59,"guildID":1047,"contributionPoint":107752451,"memberCount":51,"masterName":"Mijarane","guildLevel":6,"soldierRankID":14,"raceID":1,"gloryPointChange":1079},{"position":85,"arrowStatus":"DOWN","rankingPositionChange":-2,"characterName":"Cyniu","characterID":20073,"characterClassID":4,"gloryPoint":58306,"guildName":"Fantasy","serverName":"Miren","serverID":59,"guildID":1195,"contributionPoint":458337364,"memberCount":19,"masterName":"Livo","guildLevel":5,"soldierRankID":14,"raceID":1,"gloryPointChange":0},{"position":86,"arrowStatus":"STATIC","rankingPositionChange":-1,"characterName":"Restried","characterID":16537,"characterClassID":1,"gloryPoint":57574,"guildName":"SleepWithBeritra","serverName":"Miren","serverID":59,"guildID":1005,"contributionPoint":195469803,"memberCount":17,"masterName":"Dewuu","guildLevel":5,"soldierRankID":14,"raceID":1,"gloryPointChange":0},{"position":87,"arrowStatus":"STATIC","rankingPositionChange":-1,"characterName":"Xfearia","characterID":21601,"characterClassID":8,"gloryPoint":57400,"guildName":"Genocide","serverName":"Miren","serverID":59,"guildID":1007,"contributionPoint":651734565,"memberCount":25,"masterName":"Dargor","guildLevel":6,"soldierRankID":14,"raceID":1,"gloryPointChange":0},{"position":88,"arrowStatus":"STATIC","rankingPositionChange":0,"characterName":"Washabi","characterID":38997,"characterClassID":16,"gloryPoint":56449,"guildName":"LEGENDARNI","serverName":"Miren","serverID":59,"guildID":1567,"contributionPoint":24311790,"memberCount":30,"masterName":"Fellentia","guildLevel":5,"soldierRankID":14,"raceID":1,"gloryPointChange":3800},{"position":89,"arrowStatus":"STATIC","rankingPositionChange":1,"characterName":"Shuuri","characterID":20161,"characterClassID":10,"gloryPoint":52331,"guildName":"Stray Dogs","serverName":"Miren","serverID":59,"guildID":1563,"contributionPoint":25315856,"memberCount":16,"masterName":"Shuuri","guildLevel":5,"soldierRankID":14,"raceID":1,"gloryPointChange":1760},{"position":90,"arrowStatus":"STATIC","rankingPositionChange":-1,"characterName":"Mijarane","characterID":25484,"characterClassID":10,"gloryPoint":52071,"guildName":"Tartaros","serverName":"Miren","serverID":59,"guildID":1047,"contributionPoint":107752451,"memberCount":51,"masterName":"Mijarane","guildLevel":6,"soldierRankID":14,"raceID":1,"gloryPointChange":799},{"position":91,"arrowStatus":"STATIC","rankingPositionChange":0,"characterName":"Espix","characterID":5882,"characterClassID":8,"gloryPoint":50879,"serverName":"Miren","serverID":59,"soldierRankID":14,"raceID":1,"gloryPointChange":2950},{"position":92,"arrowStatus":"STATIC","rankingPositionChange":0,"characterName":"Tunner","characterID":22057,"characterClassID":1,"gloryPoint":47419,"guildName":"EPIDEMIA","serverName":"Miren","serverID":59,"guildID":1133,"contributionPoint":24230750,"memberCount":15,"masterName":"Zarazatwa","guildLevel":5,"soldierRankID":14,"raceID":1,"gloryPointChange":0},{"position":93,"arrowStatus":"STATIC","rankingPositionChange":0,"characterName":"Nynyny","characterID":5246,"characterClassID":4,"gloryPoint":46610,"serverName":"Miren","serverID":59,"soldierRankID":14,"raceID":1,"gloryPointChange":0},{"position":94,"arrowStatus":"UP","rankingPositionChange":2,"characterName":"Grzeszny","characterID":39953,"characterClassID":4,"gloryPoint":46510,"guildName":"Stray Dogs","serverName":"Miren","serverID":59,"guildID":1563,"contributionPoint":25315856,"memberCount":16,"masterName":"Shuuri","guildLevel":5,"soldierRankID":14,"raceID":1,"gloryPointChange":2785},{"position":95,"arrowStatus":"DOWN","rankingPositionChange":-1,"characterName":"Malpeczka","characterID":1316,"characterClassID":10,"gloryPoint":45995,"guildName":"DevastatioN","serverName":"Miren","serverID":59,"guildID":1033,"contributionPoint":267084594,"memberCount":22,"masterName":"Fuxy","guildLevel":5,"soldierRankID":14,"raceID":1,"gloryPointChange":0},{"position":96,"arrowStatus":"STATIC","rankingPositionChange":-1,"characterName":"Jessi","characterID":3503,"characterClassID":16,"gloryPoint":44092,"guildName":"Tartaros","serverName":"Miren","serverID":59,"guildID":1047,"contributionPoint":107752451,"memberCount":51,"masterName":"Mijarane","guildLevel":6,"soldierRankID":14,"raceID":1,"gloryPointChange":60},{"position":97,"arrowStatus":"STATIC","rankingPositionChange":0,"characterName":"Iminical","characterID":2145,"characterClassID":10,"gloryPoint":43083,"guildName":"Genocide","serverName":"Miren","serverID":59,"guildID":1007,"contributionPoint":651734565,"memberCount":25,"masterName":"Dargor","guildLevel":6,"soldierRankID":14,"raceID":1,"gloryPointChange":0},{"position":98,"arrowStatus":"STATIC","rankingPositionChange":0,"characterName":"Keroina","characterID":13360,"characterClassID":10,"gloryPoint":41091,"guildName":"Genocide","serverName":"Miren","serverID":59,"guildID":1007,"contributionPoint":651734565,"memberCount":25,"masterName":"Dargor","guildLevel":6,"soldierRankID":14,"raceID":1,"gloryPointChange":900},{"position":99,"arrowStatus":"STATIC","rankingPositionChange":0,"characterName":"Eviiee","characterID":22925,"characterClassID":10,"gloryPoint":39004,"guildName":"Genocide","serverName":"Miren","serverID":59,"guildID":1007,"contributionPoint":651734565,"memberCount":25,"masterName":"Dargor","guildLevel":6,"soldierRankID":14,"raceID":1,"gloryPointChange":0},{"position":100,"arrowStatus":"STATIC","rankingPositionChange":0,"characterName":"Danceme","characterID":36502,"characterClassID":16,"gloryPoint":37508,"serverName":"Miren","serverID":59,"soldierRankID":14,"raceID":1,"gloryPointChange":390},{"position":101,"arrowStatus":"STATIC","rankingPositionChange":0,"characterName":"Zgniataczjaj","characterID":18850,"characterClassID":10,"gloryPoint":35479,"guildName":"Black Salami","serverName":"Miren","serverID":59,"guildID":1234,"contributionPoint":2869145,"memberCount":1,"masterName":"Zgniataczjaj","guildLevel":1,"soldierRankID":13,"raceID":1,"gloryPointChange":0},{"position":102,"arrowStatus":"STATIC","rankingPositionChange":0,"characterName":"Lateria","characterID":4273,"characterClassID":5,"gloryPoint":35374,"guildName":"Stray Dogs","serverName":"Miren","serverID":59,"guildID":1563,"contributionPoint":25315856,"memberCount":16,"masterName":"Shuuri","guildLevel":5,"soldierRankID":13,"raceID":1,"gloryPointChange":0},{"position":103,"arrowStatus":"STATIC","rankingPositionChange":0,"characterName":"Shire","characterID":4529,"characterClassID":10,"gloryPoint":35139,"guildName":"Tartaros","serverName":"Miren","serverID":59,"guildID":1047,"contributionPoint":107752451,"memberCount":51,"masterName":"Mijarane","guildLevel":6,"soldierRankID":13,"raceID":1,"gloryPointChange":1195},{"position":104,"arrowStatus":"STATIC","rankingPositionChange":0,"characterName":"Elevated","characterID":22808,"characterClassID":4,"gloryPoint":33717,"guildName":"Fantasy","serverName":"Miren","serverID":59,"guildID":1195,"contributionPoint":458337364,"memberCount":19,"masterName":"Livo","guildLevel":5,"soldierRankID":13,"raceID":1,"gloryPointChange":180},{"position":105,"arrowStatus":"STATIC","rankingPositionChange":0,"characterName":"Pinata","characterID":33423,"characterClassID":10,"gloryPoint":32775,"guildName":"Akademia Fantasy","serverName":"Miren","serverID":59,"guildID":1316,"contributionPoint":69006594,"memberCount":74,"masterName":"Eukelade","guildLevel":5,"soldierRankID":13,"raceID":1,"gloryPointChange":1500},{"position":106,"arrowStatus":"STATIC","rankingPositionChange":0,"characterName":"Ricusss","characterID":7618,"characterClassID":2,"gloryPoint":30695,"guildName":"Tartaros","serverName":"Miren","serverID":59,"guildID":1047,"contributionPoint":107752451,"memberCount":51,"masterName":"Mijarane","guildLevel":6,"soldierRankID":13,"raceID":1,"gloryPointChange":1560},{"position":107,"arrowStatus":"STATIC","rankingPositionChange":0,"characterName":"Healena","characterID":41557,"characterClassID":10,"gloryPoint":27793,"serverName":"Miren","serverID":59,"soldierRankID":13,"raceID":1,"gloryPointChange":50},{"position":108,"arrowStatus":"UP","rankingPositionChange":4,"characterName":"Cerberusf","characterID":51529,"characterClassID":11,"gloryPoint":27393,"guildName":"Stray Dogs","serverName":"Miren","serverID":59,"guildID":1563,"contributionPoint":25315856,"memberCount":16,"masterName":"Shuuri","guildLevel":5,"soldierRankID":13,"raceID":1,"gloryPointChange":2676},{"position":109,"arrowStatus":"DOWN","rankingPositionChange":2,"characterName":"Missi","characterID":33984,"characterClassID":7,"gloryPoint":27387,"guildName":"Veni Vidi Vici","serverName":"Miren","serverID":59,"guildID":1278,"contributionPoint":41011150,"memberCount":25,"masterName":"Xclusives","guildLevel":5,"soldierRankID":13,"raceID":1,"gloryPointChange":2150},{"position":110,"arrowStatus":"UP","rankingPositionChange":3,"characterName":"Skoczek","characterID":45110,"characterClassID":11,"gloryPoint":26985,"guildName":"Rastenburg","serverName":"Miren","serverID":59,"guildID":1548,"contributionPoint":2290994,"memberCount":17,"masterName":"Skoczek","guildLevel":4,"soldierRankID":13,"raceID":1,"gloryPointChange":3050},{"position":111,"arrowStatus":"DOWN","rankingPositionChange":-3,"characterName":"Akulek","characterID":7886,"characterClassID":13,"gloryPoint":26676,"guildName":"Pathology Squad","serverName":"Miren","serverID":59,"guildID":1096,"contributionPoint":187735467,"memberCount":35,"masterName":"Lordsm","guildLevel":6,"soldierRankID":13,"raceID":1,"gloryPointChange":0},{"position":112,"arrowStatus":"DOWN","rankingPositionChange":-3,"characterName":"Prospect","characterID":14390,"characterClassID":8,"gloryPoint":26222,"guildName":"Tartaros","serverName":"Miren","serverID":59,"guildID":1047,"contributionPoint":107752451,"memberCount":51,"masterName":"Mijarane","guildLevel":6,"soldierRankID":13,"raceID":1,"gloryPointChange":0},{"position":113,"arrowStatus":"DOWN","rankingPositionChange":-3,"characterName":"Zick","characterID":43834,"characterClassID":5,"gloryPoint":26172,"guildName":" Infinity Cookies ","serverName":"Miren","serverID":59,"guildID":1571,"contributionPoint":15792595,"memberCount":26,"masterName":"Zick","guildLevel":5,"soldierRankID":13,"raceID":1,"gloryPointChange":390},{"position":114,"arrowStatus":"STATIC","rankingPositionChange":0,"characterName":"Barbasia","characterID":38297,"characterClassID":16,"gloryPoint":24757,"guildName":"LEGENDARNI","serverName":"Miren","serverID":59,"guildID":1567,"contributionPoint":24311790,"memberCount":30,"masterName":"Fellentia","guildLevel":5,"soldierRankID":13,"raceID":1,"gloryPointChange":1660},{"position":115,"arrowStatus":"STATIC","rankingPositionChange":3,"characterName":"Doomsady","characterID":32076,"characterClassID":2,"gloryPoint":23582,"guildName":"Genocide","serverName":"Miren","serverID":59,"guildID":1007,"contributionPoint":651734565,"memberCount":25,"masterName":"Dargor","guildLevel":6,"soldierRankID":13,"raceID":1,"gloryPointChange":1760},{"position":116,"arrowStatus":"STATIC","rankingPositionChange":-1,"characterName":"Shannara","characterID":32509,"characterClassID":16,"gloryPoint":22814,"guildName":"Tartaros","serverName":"Miren","serverID":59,"guildID":1047,"contributionPoint":107752451,"memberCount":51,"masterName":"Mijarane","guildLevel":6,"soldierRankID":13,"raceID":1,"gloryPointChange":0},{"position":117,"arrowStatus":"STATIC","rankingPositionChange":-1,"characterName":"Brain","characterID":49788,"characterClassID":4,"gloryPoint":22318,"guildName":" Strangers ","serverName":"Miren","serverID":59,"guildID":1516,"contributionPoint":62931896,"memberCount":13,"masterName":"Fushinka","guildLevel":5,"soldierRankID":13,"raceID":1,"gloryPointChange":0},{"position":118,"arrowStatus":"STATIC","rankingPositionChange":-1,"characterName":"Malusia","characterID":29872,"characterClassID":16,"gloryPoint":21876,"guildName":"Black Cat Club","serverName":"Miren","serverID":59,"guildID":1595,"contributionPoint":3215745,"memberCount":29,"masterName":"Sebek","guildLevel":5,"soldierRankID":13,"raceID":1,"gloryPointChange":0},{"position":119,"arrowStatus":"STATIC","rankingPositionChange":0,"characterName":"Celar","characterID":5030,"characterClassID":11,"gloryPoint":21408,"guildName":"Stray Dogs","serverName":"Miren","serverID":59,"guildID":1563,"contributionPoint":25315856,"memberCount":16,"masterName":"Shuuri","guildLevel":5,"soldierRankID":13,"raceID":1,"gloryPointChange":0},{"position":120,"arrowStatus":"STATIC","rankingPositionChange":0,"characterName":"Celebriana","characterID":33902,"characterClassID":16,"gloryPoint":20997,"guildName":"Akademia Fantasy","serverName":"Miren","serverID":59,"guildID":1316,"contributionPoint":69006594,"memberCount":74,"masterName":"Eukelade","guildLevel":5,"soldierRankID":13,"raceID":1,"gloryPointChange":0},{"position":121,"arrowStatus":"STATIC","rankingPositionChange":0,"characterName":"Koba","characterID":43386,"characterClassID":2,"gloryPoint":20687,"guildName":"Crusaders","serverName":"Miren","serverID":59,"guildID":1527,"contributionPoint":2435659,"memberCount":6,"masterName":"Koba","guildLevel":3,"soldierRankID":13,"raceID":1,"gloryPointChange":75},{"position":122,"arrowStatus":"STATIC","rankingPositionChange":4,"characterName":"Barrakuda","characterID":45293,"characterClassID":16,"gloryPoint":20455,"guildName":"Rastenburg","serverName":"Miren","serverID":59,"guildID":1548,"contributionPoint":2290994,"memberCount":17,"masterName":"Skoczek","guildLevel":4,"soldierRankID":13,"raceID":1,"gloryPointChange":3050},{"position":123,"arrowStatus":"UP","rankingPositionChange":1,"characterName":"Sopell","characterID":45406,"characterClassID":11,"gloryPoint":19606,"guildName":"Tartaros","serverName":"Miren","serverID":59,"guildID":1047,"contributionPoint":107752451,"memberCount":51,"masterName":"Mijarane","guildLevel":6,"soldierRankID":13,"raceID":1,"gloryPointChange":1050},{"position":124,"arrowStatus":"DOWN","rankingPositionChange":-2,"characterName":"Hate","characterID":51343,"characterClassID":10,"gloryPoint":19125,"guildName":"LEGENDARNI","serverName":"Miren","serverID":59,"guildID":1567,"contributionPoint":24311790,"memberCount":30,"masterName":"Fellentia","guildLevel":5,"soldierRankID":13,"raceID":1,"gloryPointChange":0},{"position":125,"arrowStatus":"DOWN","rankingPositionChange":-2,"characterName":"Arjo","characterID":23912,"characterClassID":11,"gloryPoint":19028,"guildName":"Genocide","serverName":"Miren","serverID":59,"guildID":1007,"contributionPoint":651734565,"memberCount":25,"masterName":"Dargor","guildLevel":6,"soldierRankID":13,"raceID":1,"gloryPointChange":0},{"position":126,"arrowStatus":"DOWN","rankingPositionChange":-1,"characterName":"Setka","characterID":36687,"characterClassID":11,"gloryPoint":18670,"serverName":"Miren","serverID":59,"soldierRankID":13,"raceID":1,"gloryPointChange":1000},{"position":127,"arrowStatus":"STATIC","rankingPositionChange":0,"characterName":"Nikkiwatarii","characterID":9460,"characterClassID":4,"gloryPoint":16878,"guildName":"Stray Dogs","serverName":"Miren","serverID":59,"guildID":1563,"contributionPoint":25315856,"memberCount":16,"masterName":"Shuuri","guildLevel":5,"soldierRankID":13,"raceID":1,"gloryPointChange":390},{"position":128,"arrowStatus":"STATIC","rankingPositionChange":2,"characterName":"Annwyn","characterID":27057,"characterClassID":8,"gloryPoint":16253,"guildName":"AlterEgon","serverName":"Miren","serverID":59,"guildID":1290,"contributionPoint":10159696,"memberCount":11,"masterName":"Annwyn","guildLevel":1,"soldierRankID":13,"raceID":1,"gloryPointChange":1950},{"position":129,"arrowStatus":"STATIC","rankingPositionChange":-1,"characterName":"Dame","characterID":19197,"characterClassID":11,"gloryPoint":15710,"serverName":"Miren","serverID":59,"soldierRankID":13,"raceID":1,"gloryPointChange":0},{"position":130,"arrowStatus":"STATIC","rankingPositionChange":-1,"characterName":"Bing","characterID":12731,"characterClassID":14,"gloryPoint":15510,"guildName":"LEGENDARNI","serverName":"Miren","serverID":59,"guildID":1567,"contributionPoint":24311790,"memberCount":30,"masterName":"Fellentia","guildLevel":5,"soldierRankID":13,"raceID":1,"gloryPointChange":900},{"position":131,"arrowStatus":"STATIC","rankingPositionChange":1,"characterName":"Fellentia","characterID":43802,"characterClassID":7,"gloryPoint":13785,"guildName":"LEGENDARNI","serverName":"Miren","serverID":59,"guildID":1567,"contributionPoint":24311790,"memberCount":30,"masterName":"Fellentia","guildLevel":5,"soldierRankID":13,"raceID":1,"gloryPointChange":1585},{"position":132,"arrowStatus":"STATIC","rankingPositionChange":-1,"characterName":"Rhan","characterID":1040,"characterClassID":8,"gloryPoint":12420,"serverName":"Miren","serverID":59,"soldierRankID":13,"raceID":1,"gloryPointChange":0},{"position":133,"arrowStatus":"UP","rankingPositionChange":14,"characterName":"Macabresco","characterID":51288,"characterClassID":1,"gloryPoint":12242,"guildName":"LEGENDARNI","serverName":"Miren","serverID":59,"guildID":1567,"contributionPoint":24311790,"memberCount":30,"masterName":"Fellentia","guildLevel":5,"soldierRankID":13,"raceID":1,"gloryPointChange":4111},{"position":134,"arrowStatus":"DOWN","rankingPositionChange":-1,"characterName":"Arundale","characterID":25830,"characterClassID":16,"gloryPoint":11816,"guildName":"Tartaros","serverName":"Miren","serverID":59,"guildID":1047,"contributionPoint":107752451,"memberCount":51,"masterName":"Mijarane","guildLevel":6,"soldierRankID":13,"raceID":1,"gloryPointChange":0},{"position":135,"arrowStatus":"STATIC","rankingPositionChange":4,"characterName":"Pesos","characterID":25321,"characterClassID":2,"gloryPoint":11518,"guildName":"Akademia Fantasy","serverName":"Miren","serverID":59,"guildID":1316,"contributionPoint":69006594,"memberCount":74,"masterName":"Eukelade","guildLevel":5,"soldierRankID":13,"raceID":1,"gloryPointChange":1560},{"position":136,"arrowStatus":"STATIC","rankingPositionChange":-1,"characterName":"Marcelina","characterID":4532,"characterClassID":7,"gloryPoint":11517,"guildName":"Pathology Squad","serverName":"Miren","serverID":59,"guildID":1096,"contributionPoint":187735467,"memberCount":35,"masterName":"Lordsm","guildLevel":6,"soldierRankID":13,"raceID":1,"gloryPointChange":1046},{"position":137,"arrowStatus":"UP","rankingPositionChange":6,"characterName":"Yuuuhi","characterID":53127,"characterClassID":10,"gloryPoint":11086,"guildName":"Pathology Squad","serverName":"Miren","serverID":59,"guildID":1096,"contributionPoint":187735467,"memberCount":35,"masterName":"Lordsm","guildLevel":6,"soldierRankID":13,"raceID":1,"gloryPointChange":1730},{"position":138,"arrowStatus":"DOWN","rankingPositionChange":-1,"characterName":"Prada","characterID":29427,"characterClassID":1,"gloryPoint":10578,"guildName":"Akademia Fantasy","serverName":"Miren","serverID":59,"guildID":1316,"contributionPoint":69006594,"memberCount":74,"masterName":"Eukelade","guildLevel":5,"soldierRankID":13,"raceID":1,"gloryPointChange":390},{"position":139,"arrowStatus":"DOWN","rankingPositionChange":-5,"characterName":"Peacock","characterID":27017,"characterClassID":7,"gloryPoint":10512,"guildName":"Akademia Fantasy","serverName":"Miren","serverID":59,"guildID":1316,"contributionPoint":69006594,"memberCount":74,"masterName":"Eukelade","guildLevel":5,"soldierRankID":13,"raceID":1,"gloryPointChange":0},{"position":140,"arrowStatus":"DOWN","rankingPositionChange":-2,"characterName":"Repo","characterID":8141,"characterClassID":1,"gloryPoint":10423,"guildName":"Shadows","serverName":"Miren","serverID":59,"guildID":1345,"contributionPoint":26828936,"memberCount":24,"masterName":"Gargi","guildLevel":5,"soldierRankID":13,"raceID":1,"gloryPointChange":319},{"position":141,"arrowStatus":"DOWN","rankingPositionChange":-5,"characterName":"Omnipollo","characterID":29957,"characterClassID":16,"gloryPoint":10237,"guildName":"Akademia Fantasy","serverName":"Miren","serverID":59,"guildID":1316,"contributionPoint":69006594,"memberCount":74,"masterName":"Eukelade","guildLevel":5,"soldierRankID":13,"raceID":1,"gloryPointChange":0},{"position":142,"arrowStatus":"STATIC","rankingPositionChange":-2,"characterName":"Blaszak","characterID":43747,"characterClassID":13,"gloryPoint":9994,"guildName":"Veni Vidi Vici","serverName":"Miren","serverID":59,"guildID":1278,"contributionPoint":41011150,"memberCount":25,"masterName":"Xclusives","guildLevel":5,"soldierRankID":13,"raceID":1,"gloryPointChange":103},{"position":143,"arrowStatus":"DOWN","rankingPositionChange":3,"characterName":"Dexty","characterID":51029,"characterClassID":8,"gloryPoint":9919,"serverName":"Miren","serverID":59,"soldierRankID":13,"raceID":1,"gloryPointChange":1760},{"position":144,"arrowStatus":"DOWN","rankingPositionChange":1,"characterName":"Etopiryna","characterID":50486,"characterClassID":10,"gloryPoint":9885,"guildName":"LEGENDARNI","serverName":"Miren","serverID":59,"guildID":1567,"contributionPoint":24311790,"memberCount":30,"masterName":"Fellentia","guildLevel":5,"soldierRankID":13,"raceID":1,"gloryPointChange":1685},{"position":145,"arrowStatus":"DOWN","rankingPositionChange":-4,"characterName":"Mesiash","characterID":25580,"characterClassID":10,"gloryPoint":9833,"guildName":"LEGENDARNI","serverName":"Miren","serverID":59,"guildID":1567,"contributionPoint":24311790,"memberCount":30,"masterName":"Fellentia","guildLevel":5,"soldierRankID":13,"raceID":1,"gloryPointChange":0},{"position":146,"arrowStatus":"DOWN","rankingPositionChange":-4,"characterName":"Bobon","characterID":3563,"characterClassID":4,"gloryPoint":9738,"serverName":"Miren","serverID":59,"soldierRankID":13,"raceID":1,"gloryPointChange":141},{"position":147,"arrowStatus":"STATIC","rankingPositionChange":-3,"characterName":"Szpiclowa","characterID":18289,"characterClassID":1,"gloryPoint":9180,"guildName":"Veni Vidi Vici","serverName":"Miren","serverID":59,"guildID":1278,"contributionPoint":41011150,"memberCount":25,"masterName":"Xclusives","guildLevel":5,"soldierRankID":13,"raceID":1,"gloryPointChange":0},{"position":148,"arrowStatus":"UP","rankingPositionChange":3,"characterName":"Mahisza","characterID":50354,"characterClassID":8,"gloryPoint":8797,"guildName":" Strangers ","serverName":"Miren","serverID":59,"guildID":1516,"contributionPoint":62931896,"memberCount":13,"masterName":"Fushinka","guildLevel":5,"soldierRankID":13,"raceID":1,"gloryPointChange":2565},{"position":149,"arrowStatus":"STATIC","rankingPositionChange":0,"characterName":"Kinah","characterID":50602,"characterClassID":1,"gloryPoint":8659,"guildName":"Akademia Fantasy","serverName":"Miren","serverID":59,"guildID":1316,"contributionPoint":69006594,"memberCount":74,"masterName":"Eukelade","guildLevel":5,"soldierRankID":13,"raceID":1,"gloryPointChange":1290},{"position":150,"arrowStatus":"DOWN","rankingPositionChange":-2,"characterName":"Coreks","characterID":44331,"characterClassID":4,"gloryPoint":8381,"serverName":"Miren","serverID":59,"soldierRankID":13,"raceID":1,"gloryPointChange":380},{"position":151,"arrowStatus":"UP","rankingPositionChange":-1,"characterName":"Coveric","characterID":2366,"characterClassID":7,"gloryPoint":7558,"guildName":"Pathology Squad","serverName":"Miren","serverID":59,"guildID":1096,"contributionPoint":187735467,"memberCount":35,"masterName":"Lordsm","guildLevel":6,"soldierRankID":13,"raceID":1,"gloryPointChange":900},{"position":152,"arrowStatus":"DOWN","rankingPositionChange":3,"characterName":"Reze","characterID":36303,"characterClassID":4,"gloryPoint":7144,"guildName":"All You Need Is Kill","serverName":"Miren","serverID":59,"guildID":1515,"contributionPoint":4561617,"memberCount":7,"masterName":"Izanami","guildLevel":3,"soldierRankID":13,"raceID":1,"gloryPointChange":1760},{"position":153,"arrowStatus":"DOWN","rankingPositionChange":3,"characterName":"Viscort","characterID":53597,"characterClassID":4,"gloryPoint":6842,"guildName":" Infinity Cookies ","serverName":"Miren","serverID":59,"guildID":1571,"contributionPoint":15792595,"memberCount":26,"masterName":"Zick","guildLevel":5,"soldierRankID":13,"raceID":1,"gloryPointChange":2070},{"position":154,"arrowStatus":"STATIC","rankingPositionChange":-2,"characterName":"Chrumcia","characterID":23082,"characterClassID":10,"gloryPoint":5903,"guildName":"Boje sie ciemnosci","serverName":"Miren","serverID":59,"guildID":1309,"contributionPoint":4366846,"memberCount":3,"masterName":"Swinka","guildLevel":1,"soldierRankID":13,"raceID":1,"gloryPointChange":0},{"position":155,"arrowStatus":"STATIC","rankingPositionChange":-2,"characterName":"Whiterose","characterID":53745,"characterClassID":5,"gloryPoint":5545,"guildName":" Infinity Cookies ","serverName":"Miren","serverID":59,"guildID":1571,"contributionPoint":15792595,"memberCount":26,"masterName":"Zick","guildLevel":5,"soldierRankID":13,"raceID":1,"gloryPointChange":60},{"position":156,"arrowStatus":"STATIC","rankingPositionChange":-2,"characterName":"Sapphir","characterID":47023,"characterClassID":1,"gloryPoint":5412,"guildName":"Tartaros","serverName":"Miren","serverID":59,"guildID":1047,"contributionPoint":107752451,"memberCount":51,"masterName":"Mijarane","guildLevel":6,"soldierRankID":13,"raceID":1,"gloryPointChange":0},{"position":157,"arrowStatus":"UP","rankingPositionChange":2,"characterName":"Jinzin","characterID":24131,"characterClassID":10,"gloryPoint":5200,"guildName":"Tartaros","serverName":"Miren","serverID":59,"guildID":1047,"contributionPoint":107752451,"memberCount":51,"masterName":"Mijarane","guildLevel":6,"soldierRankID":13,"raceID":1,"gloryPointChange":900},{"position":158,"arrowStatus":"DOWN","rankingPositionChange":-1,"characterName":"Longfail","characterID":27886,"characterClassID":14,"gloryPoint":4585,"guildName":"My name is Potato","serverName":"Miren","serverID":59,"guildID":1284,"contributionPoint":5308061,"memberCount":7,"masterName":"Amaja","guildLevel":5,"soldierRankID":13,"raceID":1,"gloryPointChange":0},{"position":159,"arrowStatus":"DOWN","rankingPositionChange":-1,"characterName":"Cyniuu","characterID":28739,"characterClassID":10,"gloryPoint":4448,"serverName":"Miren","serverID":59,"soldierRankID":13,"raceID":1,"gloryPointChange":0},{"position":160,"arrowStatus":"UP","rankingPositionChange":9,"characterName":"Ivan","characterID":51940,"characterClassID":7,"gloryPoint":4429,"guildName":"Tartaros","serverName":"Miren","serverID":59,"guildID":1047,"contributionPoint":107752451,"memberCount":51,"masterName":"Mijarane","guildLevel":6,"soldierRankID":13,"raceID":1,"gloryPointChange":1916},{"position":161,"arrowStatus":"DOWN","rankingPositionChange":-1,"characterName":"Vinot","characterID":51330,"characterClassID":7,"gloryPoint":4165,"guildName":" Infinity Cookies ","serverName":"Miren","serverID":59,"guildID":1571,"contributionPoint":15792595,"memberCount":26,"masterName":"Zick","guildLevel":5,"soldierRankID":13,"raceID":1,"gloryPointChange":0},{"position":162,"arrowStatus":"DOWN","rankingPositionChange":-1,"characterName":"Disney","characterID":32443,"characterClassID":10,"gloryPoint":4040,"guildName":"Muminki","serverName":"Miren","serverID":59,"guildID":1358,"contributionPoint":13469505,"memberCount":8,"masterName":"Disney","guildLevel":5,"soldierRankID":13,"raceID":1,"gloryPointChange":0},{"position":163,"arrowStatus":"DOWN","rankingPositionChange":-1,"characterName":"Cyniuuuu","characterID":32007,"characterClassID":16,"gloryPoint":3950,"serverName":"Miren","serverID":59,"soldierRankID":13,"raceID":1,"gloryPointChange":0},{"position":164,"arrowStatus":"DOWN","rankingPositionChange":4,"characterName":"Hajzel","characterID":51001,"characterClassID":10,"gloryPoint":3949,"guildName":"Shadows","serverName":"Miren","serverID":59,"guildID":1345,"contributionPoint":26828936,"memberCount":24,"masterName":"Gargi","guildLevel":5,"soldierRankID":13,"raceID":1,"gloryPointChange":1385},{"position":165,"arrowStatus":"DOWN","rankingPositionChange":-2,"characterName":"Laurana","characterID":45231,"characterClassID":2,"gloryPoint":3948,"serverName":"Miren","serverID":59,"soldierRankID":13,"raceID":1,"gloryPointChange":80},{"position":166,"arrowStatus":"DOWN","rankingPositionChange":6,"characterName":"Xento","characterID":52221,"characterClassID":8,"gloryPoint":3800,"guildName":"LEGENDARNI","serverName":"Miren","serverID":59,"guildID":1567,"contributionPoint":24311790,"memberCount":30,"masterName":"Fellentia","guildLevel":5,"soldierRankID":13,"raceID":1,"gloryPointChange":1925},{"position":167,"arrowStatus":"DOWN","rankingPositionChange":-3,"characterName":"Shanalisica","characterID":17639,"characterClassID":4,"gloryPoint":3391,"guildName":"Stray Dogs","serverName":"Miren","serverID":59,"guildID":1563,"contributionPoint":25315856,"memberCount":16,"masterName":"Shuuri","guildLevel":5,"soldierRankID":13,"raceID":1,"gloryPointChange":0},{"position":168,"arrowStatus":"STATIC","rankingPositionChange":-1,"characterName":"Sasynek","characterID":50587,"characterClassID":4,"gloryPoint":3327,"serverName":"Miren","serverID":59,"soldierRankID":13,"raceID":1,"gloryPointChange":562},{"position":169,"arrowStatus":"STATIC","rankingPositionChange":-3,"characterName":"Agarres","characterID":51014,"characterClassID":7,"gloryPoint":3211,"guildName":"Shadows","serverName":"Miren","serverID":59,"guildID":1345,"contributionPoint":26828936,"memberCount":24,"masterName":"Gargi","guildLevel":5,"soldierRankID":13,"raceID":1,"gloryPointChange":429},{"position":170,"arrowStatus":"STATIC","rankingPositionChange":4,"characterName":"Cyniuuu","characterID":32002,"characterClassID":1,"gloryPoint":3170,"guildName":"Akademia Fantasy","serverName":"Miren","serverID":59,"guildID":1316,"contributionPoint":69006594,"memberCount":74,"masterName":"Eukelade","guildLevel":5,"soldierRankID":13,"raceID":1,"gloryPointChange":1560},{"position":171,"arrowStatus":"STATIC","rankingPositionChange":-6,"characterName":"Placek","characterID":51356,"characterClassID":10,"gloryPoint":3109,"guildName":" Infinity Cookies ","serverName":"Miren","serverID":59,"guildID":1571,"contributionPoint":15792595,"memberCount":26,"masterName":"Zick","guildLevel":5,"soldierRankID":13,"raceID":1,"gloryPointChange":0},{"position":172,"arrowStatus":"STATIC","rankingPositionChange":0,"characterName":"Soul","characterID":28837,"characterClassID":11,"gloryPoint":2730,"guildName":"Veni Vidi Vici","serverName":"Miren","serverID":59,"guildID":1278,"contributionPoint":41011150,"memberCount":25,"masterName":"Xclusives","guildLevel":5,"soldierRankID":12,"raceID":1,"gloryPointChange":0},{"position":173,"arrowStatus":"STATIC","rankingPositionChange":-3,"characterName":"Linthas","characterID":33335,"characterClassID":10,"gloryPoint":2500,"guildName":"AlterEgon","serverName":"Miren","serverID":59,"guildID":1290,"contributionPoint":10159696,"memberCount":11,"masterName":"Annwyn","guildLevel":1,"soldierRankID":12,"raceID":1,"gloryPointChange":390},{"position":174,"arrowStatus":"UP","rankingPositionChange":-1,"characterName":"Pvpsp","characterID":15367,"characterClassID":5,"gloryPoint":2254,"guildName":"Gorasul","serverName":"Miren","serverID":59,"guildID":1024,"contributionPoint":13777659,"memberCount":28,"masterName":"Leelah","guildLevel":4,"soldierRankID":12,"raceID":1,"gloryPointChange":450},{"position":175,"arrowStatus":"DOWN","rankingPositionChange":-1,"characterName":"Anris","characterID":20352,"characterClassID":10,"gloryPoint":2190,"guildName":" Infinity Cookies ","serverName":"Miren","serverID":59,"guildID":1571,"contributionPoint":15792595,"memberCount":26,"masterName":"Zick","guildLevel":5,"soldierRankID":12,"raceID":1,"gloryPointChange":0},{"position":176,"arrowStatus":"UP","rankingPositionChange":-1,"characterName":"Aurel","characterID":52049,"characterClassID":13,"gloryPoint":2139,"guildName":"Black Cat Club","serverName":"Miren","serverID":59,"guildID":1595,"contributionPoint":3215745,"memberCount":29,"masterName":"Sebek","guildLevel":5,"soldierRankID":12,"raceID":1,"gloryPointChange":544},{"position":177,"arrowStatus":"DOWN","rankingPositionChange":-2,"characterName":"Fearanka","characterID":14058,"characterClassID":8,"gloryPoint":2130,"serverName":"Miren","serverID":59,"soldierRankID":12,"raceID":1,"gloryPointChange":0},{"position":178,"arrowStatus":"DOWN","rankingPositionChange":-7,"characterName":"Milesa","characterID":31344,"characterClassID":4,"gloryPoint":2083,"guildName":"Black Cat Club","serverName":"Miren","serverID":59,"guildID":1595,"contributionPoint":3215745,"memberCount":29,"masterName":"Sebek","guildLevel":5,"soldierRankID":12,"raceID":1,"gloryPointChange":50},{"position":179,"arrowStatus":"STATIC","rankingPositionChange":0,"characterName":"Roksana","characterID":44899,"characterClassID":10,"gloryPoint":1850,"guildName":"LEGENDARNI","serverName":"Miren","serverID":59,"guildID":1567,"contributionPoint":24311790,"memberCount":30,"masterName":"Fellentia","guildLevel":5,"soldierRankID":11,"raceID":1,"gloryPointChange":0},{"position":180,"arrowStatus":"STATIC","rankingPositionChange":-4,"characterName":"Nieobecnymag","characterID":51550,"characterClassID":7,"gloryPoint":1535,"guildName":"LEGENDARNI","serverName":"Miren","serverID":59,"guildID":1567,"contributionPoint":24311790,"memberCount":30,"masterName":"Fellentia","guildLevel":5,"soldierRankID":11,"raceID":1,"gloryPointChange":0},{"position":181,"arrowStatus":"STATIC","rankingPositionChange":0,"characterName":"Siupakabra","characterID":38144,"characterClassID":10,"gloryPoint":1510,"serverName":"Miren","serverID":59,"soldierRankID":11,"raceID":1,"gloryPointChange":0}],"stats":{"elyos":{"topHP":{"characterName":"Madara","characterID":1259,"guildName":"White Shadow","guildID":1281,"gloryPointChange":5928},"topPositionChange":{"characterName":"Aretuza","characterID":16455,"guildName":"  C H U L I G A N K A  ","guildID":1057,"rankingPositionChange":3},"lowerPositionChange":{"characterName":"Piremann","characterID":35709,"guildName":"  C H U L I G A N K A  ","guildID":1057,"rankingPositionChange":-3}},"asmodians":{"topHP":{"characterName":"Kanade","characterID":17685,"guildName":" Strangers ","guildID":1516,"gloryPointChange":11014},"topPositionChange":{"characterName":"Macabresco","characterID":51288,"guildName":"LEGENDARNI","guildID":1567,"rankingPositionChange":14},"lowerPositionChange":{"characterName":"Milesa","characterID":31344,"guildName":"Black Cat Club","guildID":1595,"rankingPositionChange":-7,"serverName":"Miren","serverId":59}}}}